Workbook

Sheet Formulas
A1: Final outputs | E1: % marginal | F1: MVPF | G1: Resource cost per ton | H1: Government cost per ton | I1: Social cost per ton | M1: MVPF numerator | N1: CO2e reduction benefits | O1: Air pollution reduction benefits | P1: Transfers | R1: Social cost | S1: Govt cost | T1: Subsidy cost | U1: Extra VAT (Energy) | V1: Lost VAT (Boiler Purchase) | W1: Climate change FE | X1: ETS revenue change | Y1: Net private cost | AA1: Transfers | AB1: CO2 benefits | AC1: Air pollution | AD1: Total benefits | AF1: Subsidy cost | AG1: Lost VAT (boiler purchase) | AH1: Extra VAT (energy) | AI1: Extra ETS | AJ1: Climate change FE | AK1: Total Govt Cost | AM1: =R1& " per £7.5k" | AN1: =Y1& " per £7.5k"
D2: BUS | E2: 0.25 | F2: =M2/S2 | G2: =Y2/sum(F$9:Z$9) | H2: =S2/(sum(F$9:Z$9)*E2) | I2: =R2/sum(F$9:Z$9) | M2: =sum(N2:P2) | N2: =E2*F$17 | O2: =E2*F$23 | P2: =(1-50%*E2)*F$126 | R2: =Y2-O2+sum(U2:X2) | S2: =sum(T2:X2) | T2: =F$126 | U2: =-F$71*E2 | V2: =-$F$73*E2 | W2: =-$F$19*E2 | X2: 0 | Y2: =F125-F127+F66 | AA2: =P2/$F$126 | AB2: =N2/$F$126 | AC2: =O2/$F$126 | AD2: =M2/$F$126 | AF2: =T2/$F$126 | AG2: =V2/$F$126 | AH2: =U2/$F$126 | AI2: =X2/$F$126 | AJ2: =W2/$F$126 | AK2: =S2/$F$126 | AM2: =R2/$F$126 | AN2: =Y2/$F$126
D3: BUS | E3: 0.5 | F3: =M3/S3 | G3: =Y3/sum(F$9:Z$9) | H3: =S3/(sum(F$9:Z$9)*E3) | I3: =R3/sum(F$9:Z$9) | M3: =sum(N3:P3) | N3: =E3*F$17 | O3: =E3*F$23 | P3: =(1-50%*E3)*F$126 | R3: =Y3-O3+sum(U3:X3) | S3: =sum(T3:X3) | T3: =F$126 | U3: =-F$71*E3 | V3: =-$F$73*E3 | W3: =-$F$19*E3 | X3: 0 | Y3: =F125-F127+F66 | AA3: =P3/$F$126 | AB3: =N3/$F$126 | AC3: =O3/$F$126 | AD3: =M3/$F$126 | AF3: =T3/$F$126 | AG3: =V3/$F$126 | AH3: =U3/$F$126 | AI3: =X3/$F$126 | AJ3: =W3/$F$126 | AK3: =S3/$F$126 | AM3: =R3/$F$126 | AN3: =Y3/$F$126
D4: BUS + Cosy | E4: 0.5 | F4: =M4/S4 | G4: =Y4/sum(F$9:Z$9) | H4: =S4/(sum(F$9:Z$9)*E4) | I4: =R4/sum(F$9:Z$9) | M4: =sum(N4:P4) | N4: =E4*(F$17+F18) | O4: =E4*F$23 | P4: =(1-50%*E4)*F$126 | R4: =Y4-O4+sum(U4:X4) | S4: =sum(T4:X4) | T4: =F$126 | U4: =-(F$71 + F38) * E4 | V4: =-$F$73*E4 | W4: =-$F$19*E4 | X4: 0 | Y4: =F125-F127+F66+F67 | AA4: =P4/$F$126 | AB4: =N4/$F$126 | AC4: =O4/$F$126 | AD4: =M4/$F$126 | AF4: =T4/$F$126 | AG4: =V4/$F$126 | AH4: =U4/$F$126 | AI4: =X4/$F$126 | AJ4: =W4/$F$126 | AK4: =S4/$F$126 | AM4: =R4/$F$126 | AN4: =Y4/$F$126
A6: Intermediate Outputs | C6: Constants | D6: 2022 | E6: 2023 | F6: 2024 | G6: 2025 | H6: 2026 | I6: 2027 | J6: 2028 | K6: 2029 | L6: 2030 | M6: 2031 | N6: 2032 | O6: 2033 | P6: 2034 | Q6: 2035 | R6: 2036 | S6: 2037 | T6: 2038 | U6: 2039 | V6: 2040 | W6: 2041 | X6: 2042 | Y6: 2043
B7: Assumed consumer price change from BUS | C7: =F126 / sum(F125:F126)
B9: Carbon savings (HP) (tonnes CO2e) | C9: =sum(F9:Z9) | F9: =($C109 * $C117 + $C108 * F116) / 1000 * -1 | G9: =($C109*$C117+$C108*G116)/1000 * -1 | H9: =($C109*$C117+$C108*H116)/1000 * -1 | I9: =($C109*$C117+$C108*I116)/1000 * -1 | J9: =($C109*$C117+$C108*J116)/1000 * -1 | K9: =($C109*$C117+$C108*K116)/1000 * -1 | L9: =($C109*$C117+$C108*L116)/1000 * -1 | M9: =($C109*$C117+$C108*M116)/1000 * -1 | N9: =($C109*$C117+$C108*N116)/1000 * -1 | ... Y9: =($C109*$C117+$C108*Y116)/1000 * -1
B10: £ CO2e savings (HP) | D10: =sum(F$9:Z$9) | F10: =F9*F$94 | G10: =G9*G$94 | H10: =H9*H$94 | I10: =I9*I$94 | J10: =J9*J$94 | K10: =K9*K$94 | L10: =L9*L$94 | M10: =M9*M$94 | ... Y10: =Y9*Y$94
B11: £ CO2e savings back to HMT (HP) | F11: =$C$104*$C$105*F10 | G11: =$C$104*$C$105*G10 | H11: =$C$104*$C$105*H10 | I11: =$C$104*$C$105*I10 | J11: =$C$104*$C$105*J10 | K11: =$C$104*$C$105*K10 | L11: =$C$104*$C$105*L10 | M11: =$C$104*$C$105*M10 | ... Y11: =$C$104*$C$105*Y10
B13: Carbon savings (Cosy) (tonnes CO2e) | C13: =sum(F13:Z13) | F13: =($F147*$C157*F152 + $F148*$C158*F153 + $F149*$C159*F154 + $F150*$C160*F155) * 365 / 1000 * -1 | G13: =($F147*$C157*G152 + $F148*$C158*G153 + $F149*$C159*G154 + $F150*$C160*G155) * 365 / 1000 * -1 | H13: =($F147*$C157*H152 + $F148*$C158*H153 + $F149*$C159*H154 + $F150*$C160*H155) * 365 / 1000 * -1 | I13: =($F147*$C157*I152 + $F148*$C158*I153 + $F149*$C159*I154 + $F150*$C160*I155) * 365 / 1000 * -1 | J13: =($F147*$C157*J152 + $F148*$C158*J153 + $F149*$C159*J154 + $F150*$C160*J155) * 365 / 1000 * -1 | K13: =($F147*$C157*K152 + $F148*$C158*K153 + $F149*$C159*K154 + $F150*$C160*K155) * 365 / 1000 * -1 | L13: =($F147*$C157*L152 + $F148*$C158*L153 + $F149*$C159*L154 + $F150*$C160*L155) * 365 / 1000 * -1 | M13: =($F147*$C157*M152 + $F148*$C158*M153 + $F149*$C159*M154 + $F150*$C160*M155) * 365 / 1000 * -1 | ... Y13: =($F147*$C157*Y152 + $F148*$C158*Y153 + $F149*$C159*Y154 + $F150*$C160*Y155) * 365 / 1000 * -1
B14: £ CO2e savings (Cosy) | F14: =F13*F$94 | G14: =G13*G$94 | H14: =H13*H$94 | I14: =I13*I$94 | J14: =J13*J$94 | K14: =K13*K$94 | L14: =L13*L$94 | M14: =M13*M$94 | ... Y14: =Y13*Y$94
B15: £ CO2e savings back to HMT (Cosy) | F15: =$C$104*$C$105*F14 | G15: =$C$104*$C$105*G14 | H15: =$C$104*$C$105*H14 | I15: =$C$104*$C$105*I14 | J15: =$C$104*$C$105*J14 | K15: =$C$104*$C$105*K14 | L15: =$C$104*$C$105*L14 | M15: =$C$104*$C$105*M14 | ... Y15: =$C$104*$C$105*Y14
B17: NPV HP CO2 benefits over 20 years | F17: {=F10 + npv(C$91,G10:Z10)}
B18: NPV Cosy CO2 benefits over 20 years | F18: {=F14+npv(C$91,G14:Z14)}
B19: NPV HP CO2e savings back to HMT | F19: =F11+npv(C$91,G11:Z11)
B20: NPV Cosy CO2e savings back to HMT | F20: =F12+npv(C$91,G12:Z12)
B22: £ air pollutant change (HP – positive is benefits) | F22: =-1 * (F108*F119 + F109*F120) | G22: =-1 * (G108*G119 + G109*G120) | H22: =-1 * (H108*H119 + H109*H120) | I22: =-1 * (I108*I119 + I109*I120) | J22: =-1 * (J108*J119 + J109*J120) | K22: =-1 * (K108*K119 + K109*K120) | L22: =-1 * (L108*L119 + L109*L120) | M22: =-1 * (M108*M119 + M109*M120) | ... Y22: =-1 * (Y108*Y119 + Y109*Y120)
B23: NPV air pollutant reduction over 20 years | F23: {=F22+npv(C$91,G22:Z22)}
B25: Year | F25: 2024 | G25: 2025 | H25: 2026 | I25: 2027 | J25: 2028 | K25: 2029 | L25: 2030 | M25: 2031 | N25: 2032 | O25: 2033 | P25: 2034 | Q25: 2035 | R25: 2036 | S25: 2037 | T25: 2038 | U25: 2039 | V25: 2040 | W25: 2041 | X25: 2042 | Y25: 2043
B26: CO2 + air pollution benefits | F26: =F22+F10 | G26: =G22+G10 | H26: =H22+H10 | I26: =I22+I10 | J26: =J22+J10 | K26: =K22+K10 | L26: =L22+L10 | M26: =M22+M10 | ... Y26: =Y22+Y10
B27: CO2 + air pollution benefits (discounted) | F27: =F26 | G27: =G26/(1+$C$91)^(G6-$F$6) | H27: =H26/(1+$C$91)^(H6-$F$6) | I27: =I26/(1+$C$91)^(I6-$F$6) | J27: =J26/(1+$C$91)^(J6-$F$6) | K27: =K26/(1+$C$91)^(K6-$F$6) | L27: =L26/(1+$C$91)^(L6-$F$6) | M27: =M26/(1+$C$91)^(M6-$F$6) | N27: =N26/(1+$C$91)^(N6-$F$6) | ... Y27: =Y26/(1+$C$91)^(Y6-$F$6)
B29: HP op ex £ change to customer using Octo prices (positive means HP costs more, negative means less) | F29: =$C$109*F132+$C$108*F130 | G29: =$C$109*G132+$C$108*G130 | H29: =$C$109*H132+$C$108*H130 | I29: =$C$109*I132+$C$108*I130 | J29: =$C$109*J132+$C$108*J130 | K29: =$C$109*K132+$C$108*K130 | L29: =$C$109*L132+$C$108*L130 | M29: =$C$109*M132+$C$108*M130 | ... Y29: =$C$109*Y132+$C$108*Y130
B30: HP op ex £ change to customer if gas standing charge is eliminated using Octo prices (positive means HP costs more, negative means less) | F30: =F29-F133*365 | G30: =G29-G133*365 | H30: =H29-H133*365 | I30: =I29-I133*365 | J30: =J29-J133*365 | K30: =K29-K133*365 | L30: =L29-L133*365 | M30: =M29-M133*365 | ... Y30: =Y29-Y133*365
B31: HP op ex £ change to customer using HMG prices (positive means HP costs more, negative means less) | F31: =$C$108*F134 + $C$109*F135 | G31: =$C$108*G134 + $C$109*G135 | H31: =$C$108*H134 + $C$109*H135 | I31: =$C$108*I134 + $C$109*I135 | J31: =$C$108*J134 + $C$109*J135 | K31: =$C$108*K134 + $C$109*K135 | L31: =$C$108*L134 + $C$109*L135 | M31: =$C$108*M134 + $C$109*M135 | ... Y31: =$C$108*Y134 + $C$109*Y135
B32: HP op ex £ change to customer if gas standing charge is eliminated using HMG prices (positive means HP costs more, negative means less) | F32: =F31-F133*365 | G32: =G31-G133*365 | H32: =H31-H133*365 | I32: =I31-I133*365 | J32: =J31-J133*365 | K32: =K31-K133*365 | L32: =L31-L133*365 | M32: =M31-M133*365 | ... Y32: =Y31-Y133*365
B34: Cosy £ structural winnings (negative means savings) | F34: =($F142*$C157*($F162-$F163) + $F143*$C158*($F163-$F163) + $F144*$C159*($F164-$F163) + $F145*$C160*($F164-$F163))*365 | G34: =($F142*$C157*($F162-$F163) + $F143*$C158*($F163-$F163) + $F144*$C159*($F164-$F163) + $F145*$C160*($F164-$F163))*365 | H34: =($F142*$C157*($F162-$F163) + $F143*$C158*($F163-$F163) + $F144*$C159*($F164-$F163) + $F145*$C160*($F164-$F163))*365 | I34: =($F142*$C157*($F162-$F163) + $F143*$C158*($F163-$F163) + $F144*$C159*($F164-$F163) + $F145*$C160*($F164-$F163))*365 | J34: =($F142*$C157*($F162-$F163) + $F143*$C158*($F163-$F163) + $F144*$C159*($F164-$F163) + $F145*$C160*($F164-$F163))*365 | K34: =($F142*$C157*($F162-$F163) + $F143*$C158*($F163-$F163) + $F144*$C159*($F164-$F163) + $F145*$C160*($F164-$F163))*365 | L34: =($F142*$C157*($F162-$F163) + $F143*$C158*($F163-$F163) + $F144*$C159*($F164-$F163) + $F145*$C160*($F164-$F163))*365 | M34: =($F142*$C157*($F162-$F163) + $F143*$C158*($F163-$F163) + $F144*$C159*($F164-$F163) + $F145*$C160*($F164-$F163))*365 | ... Y34: =($F142*$C157*($F162-$F163) + $F143*$C158*($F163-$F163) + $F144*$C159*($F164-$F163) + $F145*$C160*($F164-$F163))*365
B35: Cosy £ behaviour change (negative means savings) | F35: =($F147*$C157*$F162 + $F148*$C158*$F163 + $F149*$C159*$F164 + $F150*$C160*$F164)*365 | G35: =($F147*$C157*$F162 + $F148*$C158*$F163 + $F149*$C159*$F164+$F150*$C160*$F164)*365 | H35: =($F147*$C157*$F162 + $F148*$C158*$F163 + $F149*$C159*$F164+$F150*$C160*$F164)*365 | I35: =($F147*$C157*$F162 + $F148*$C158*$F163 + $F149*$C159*$F164+$F150*$C160*$F164)*365 | J35: =($F147*$C157*$F162 + $F148*$C158*$F163 + $F149*$C159*$F164+$F150*$C160*$F164)*365 | K35: =($F147*$C157*$F162 + $F148*$C158*$F163 + $F149*$C159*$F164+$F150*$C160*$F164)*365 | L35: =($F147*$C157*$F162 + $F148*$C158*$F163 + $F149*$C159*$F164+$F150*$C160*$F164)*365 | M35: =($F147*$C157*$F162 + $F148*$C158*$F163 + $F149*$C159*$F164+$F150*$C160*$F164)*365 | N35: =($F147*$C157*$F162 + $F148*$C158*$F163 + $F149*$C159*$F164+$F150*$C160*$F164)*365 | ... Y35: =($F147*$C157*$F162 + $F148*$C158*$F163 + $F149*$C159*$F164+$F150*$C160*$F164)*365
B36: Cosy £ total (negative means savings) | F36: =sum(F34:F35) | G36: =sum(G34:G35) | H36: =sum(H34:H35) | I36: =sum(I34:I35) | J36: =sum(J34:J35) | K36: =sum(K34:K35) | L36: =sum(L34:L35) | M36: =sum(M34:M35) | ... Y36: =sum(Y34:Y35)
B37: VAT on elec changed (negative is loss) from Cosy | F37: =F36*5% | G37: =G36*5% | H37: =H36*5% | I37: =I36*5% | J37: =J36*5% | K37: =K36*5% | L37: =L36*5% | M37: =M36*5% | ... Y37: =Y36*5%
B38: NPV change (negative is loss) in VAT revenue elec from Cosy | F38: {=F37+ npv(C$91,G37:Z37)}
B40: HP pre-adoption tons CO2 | C40: =sum(F40:Y40) | F40: =($F$112*F$116+$F$113*$C$117) / 1000 | G40: =($F$112*G$116+$F$113*$C$117) / 1000 | H40: =($F$112*H$116+$F$113*$C$117) / 1000 | I40: =($F$112*I$116+$F$113*$C$117) / 1000 | J40: =($F$112*J$116+$F$113*$C$117) / 1000 | K40: =($F$112*K$116+$F$113*$C$117) / 1000 | L40: =($F$112*L$116+$F$113*$C$117) / 1000 | M40: =($F$112*M$116+$F$113*$C$117) / 1000 | ... Y40: =($F$112*Y$116+$F$113*$C$117) / 1000
B41: HP CO2 reduction in % | C41: =C9/C40 | F41: =F9/F40 | G41: =G9/G40 | H41: =H9/H40 | I41: =I9/I40 | J41: =J9/J40 | K41: =K9/K40 | L41: =L9/L40 | M41: =M9/M40 | ... Y41: =Y9/Y40
B43: HP elec consumption change in % | F43: =C108/F112
B44: HP gas consumption change in % | F44: =C109/F113
B45: HP energy consumption change in % | F45: =C110/F114
B47: HP pre-adoption energy consumption costs | F47: =F112*F130 + F113*F132 + 365*(F131+F133)
B49: Cosy pre-adoption consumption (kWh) | F49: =($F142*$C157 + $F143*$C158 + $F144*$C159 + $F145*$C160)*365
B50: Cosy pre-adoption elec costs per year (£) | F50: =F49*F163 + F131*365
B51: Cosy savings (% of costs) | F51: =F36/F50
B53: Peak period reduction per half-hour (%) | F53: =F147/F142
B54: Other period reduction per half-hour (%) | F54: =F148/F143
B55: Cosy morning increase per half-hour (%) | F55: =F149/F144
B56: Cosy afternoon increase per half-hour (%) | F56: =F150/F145
B58: Peak period elasticity | F58: =F53/50%
B59: Other period elasticity
B60: Cosy morning elasticity | F60: =F55/-50%
B61: Cosy afternoon elasticity | F61: =F56/-50%
B63: HP (HMG prices) + Cosy £ change to customer | F63: =F31+F36 | G63: =G31+G36 | H63: =H31+H36 | I63: =I31+I36 | J63: =J31+J36 | K63: =K31+K36 | L63: =L31+L36 | M63: =M31+M36 | ... Y63: =Y31+Y36
B64: HP + Cosy £ change to customer if gas standing charge is eliminated | F64: =F32+F36 | G64: =G32+G36 | H64: =H32+H36 | I64: =I32+I36 | J64: =J32+J36 | K64: =K32+K36 | L64: =L32+L36 | M64: =M32+M36 | ... Y64: =Y32+Y36
B66: NPV running costs to customer of HP if gas standing charge eliminated (positive means costs) | F66: {=(F32+ npv(C$91,G32:Z32))}
B67: NPV running costs to customer of Cosy | F67: {=F36+ npv(C$91,G36:Z36)}
B68: Net private cost of the heat pump
B70: Change in VAT on energy (op ex) revenue for Govt (positive means extra; negative means less) | F70: =5% * (C108*F134 + C109*F135) | G70: =5%* (D108*G134 + D109*G135) | H70: =5%* (E108*H134 + E109*H135) | I70: =5%* (F108*I134 + F109*I135) | J70: =5%* (G108*J134 + G109*J135) | K70: =5%* (H108*K134 + H109*K135) | L70: =5%* (I108*L134 + I109*L135) | M70: =5%* (J108*M134 + J109*M135) | N70: =5%* (K108*N134 + K109*N135) | ... Y70: =5%* (V108*Y134 + V109*Y135)
B71: NPV change in VAT revenue energy | F71: {=F70+ npv(C$91,G70:Z70)}
B73: Change in VAT from boiler 20% vs HP 0% / 5% | F73: =-20%*$F$128 + 0%*$F$125
B75: Change in ETS revenue (positive means extra) | F75: =F108*F116*F102 / 1000 | G75: =G108*G116*G102 / 1000 | H75: =H108*H116*H102 / 1000 | I75: =I108*I116*I102 / 1000 | J75: =J108*J116*J102 / 1000 | K75: =K108*K116*K102 / 1000 | L75: =L108*L116*L102 / 1000 | M75: =M108*M116*M102 / 1000 | ... Y75: =Y108*Y116*Y102 / 1000
B76: NPV change in ETS revenue | F76: {=F75+npv(C$91,G75:Z75)}
B78: Total FEs | F78: =F76+F73+F71+F19
B80: HP gas decrease as % of elec increase | C80: =C109/C108
B82: Wholesale costs savings (Cosy) | D82: =($F147*$C157*D166 + $F148*$C158*D167 + $F149*$C159*D168 + $F150*$C160*D169)*365 | E82: =($F147*$C157*E166 + $F148*$C158*E167 + $F149*$C159*E168 + $F150*$C160*E169)*365 | F82: =($F147*$C157*F166 + $F148*$C158*F167 + $F149*$C159*F168 + $F150*$C160*F169)*365
B84: LBD enviro benefits 3.5% discount rate | C84: 3192.62 | D84: =C84/7500
B85: LBD price benefits 3.5% discount rate | C85: 1697.59 | D85: =C85/7500
B86: MVPF numerator if including the LBD benefits | C86: =M3+sum(C84:C85)
B87: MVPF | C87: =C86/S3
A90: Inputs | C90: Constants | D90: 2022 | E90: 2023 | F90: 2024 | G90: 2025 | H90: 2026 | I90: 2027 | J90: 2028 | K90: 2029 | L90: 2030 | M90: 2031 | N90: 2032 | O90: 2033 | P90: 2034 | Q90: 2035 | R90: 2036 | S90: 2037 | T90: 2038 | U90: 2039 | V90: 2040 | W90: 2041 | X90: 2042 | Y90: 2043
B91: Discount rate | C91: 0.035
B92: Discount rate for air quality costs/benefits | C92: 0.015
B94: SCC used in calculations | D94: =D96 | E94: =E96 | F94: =F96 | G94: =G96 | H94: =H96 | I94: =I96 | J94: =J96 | K94: =K96 | ... Y94: =Y96
B95: Carbon value (£2020) | D95: =VLOOKUP(D$6,'SCC HMG'!$A$4:$D$35,3,false) | E95: =VLOOKUP(E6,'SCC HMG'!$A$4:$D$35,3,false) | F95: =VLOOKUP(F6,'SCC HMG'!$A$4:$D$35,3,false) | G95: =VLOOKUP(G6,'SCC HMG'!$A$4:$D$35,3,false) | H95: =VLOOKUP(H6,'SCC HMG'!$A$4:$D$35,3,false) | I95: =VLOOKUP(I6,'SCC HMG'!$A$4:$D$35,3,false) | J95: =VLOOKUP(J6,'SCC HMG'!$A$4:$D$35,3,false) | K95: =VLOOKUP(K6,'SCC HMG'!$A$4:$D$35,3,false) | L95: =VLOOKUP(L6,'SCC HMG'!$A$4:$D$35,3,false) | ... Y95: =VLOOKUP(Y6,'SCC HMG'!$A$4:$D$35,3,false)
B96: Carbon value (£2023) | D96: =D95/('GDP deflator'!$I$76/'GDP deflator'!$I$79) | E96: =E95/('GDP deflator'!$I$76/'GDP deflator'!$I$79) | F96: =F95/('GDP deflator'!$I$76/'GDP deflator'!$I$79) | G96: =G95/('GDP deflator'!$I$76/'GDP deflator'!$I$79) | H96: =H95/('GDP deflator'!$I$76/'GDP deflator'!$I$79) | I96: =I95/('GDP deflator'!$I$76/'GDP deflator'!$I$79) | J96: =J95/('GDP deflator'!$I$76/'GDP deflator'!$I$79) | K96: =K95/('GDP deflator'!$I$76/'GDP deflator'!$I$79) | ... Y96: =Y95/('GDP deflator'!$I$76/'GDP deflator'!$I$79)
B97: Carbon value (IWG, $2021) | D97: =VLOOKUP(D6,'SCC IWG'!$B$3:$E$34,3,false) | E97: =VLOOKUP(E6,'SCC IWG'!$B$3:$E$34,3,false) | F97: =VLOOKUP(F6,'SCC IWG'!$B$3:$E$34,3,false) | G97: =VLOOKUP(G6,'SCC IWG'!$B$3:$E$34,3,false) | H97: =VLOOKUP(H6,'SCC IWG'!$B$3:$E$34,3,false) | I97: =VLOOKUP(I6,'SCC IWG'!$B$3:$E$34,3,false) | J97: =VLOOKUP(J6,'SCC IWG'!$B$3:$E$34,3,false) | K97: =VLOOKUP(K6,'SCC IWG'!$B$3:$E$34,3,false) | ... Y97: =VLOOKUP(Y6,'SCC IWG'!$B$3:$E$34,3,false)
B98: USD per GBP | C98: 0.8
B99: Carbon value (IWG, £2021) | D99: =D97*$C98 | E99: =E97*$C98 | F99: =F97*$C98 | G99: =G97*$C98 | H99: =H97*$C98 | I99: =I97*$C98 | J99: =J97*$C98 | K99: =K97*$C98 | ... Y99: =Y97*$C98
B100: Carbon value (IWG, £2023) | D100: =D99/('GDP deflator'!$I$77/'GDP deflator'!$I$79) | E100: =E99/('GDP deflator'!$I$77/'GDP deflator'!$I$79) | F100: =F99/('GDP deflator'!$I$77/'GDP deflator'!$I$79) | G100: =G99/('GDP deflator'!$I$77/'GDP deflator'!$I$79) | H100: =H99/('GDP deflator'!$I$77/'GDP deflator'!$I$79) | I100: =I99/('GDP deflator'!$I$77/'GDP deflator'!$I$79) | J100: =J99/('GDP deflator'!$I$77/'GDP deflator'!$I$79) | K100: =K99/('GDP deflator'!$I$77/'GDP deflator'!$I$79) | ... Y100: =Y99/('GDP deflator'!$I$77/'GDP deflator'!$I$79)
B102: UK ETS £(2023) per ton CO2e | F102: =VLOOKUP(F6,'UK ETS'!$A$6:$E$35,2,false) | G102: =VLOOKUP(G6,'UK ETS'!$A$6:$E$35,2,false) | H102: =VLOOKUP(H6,'UK ETS'!$A$6:$E$35,2,false) | I102: =VLOOKUP(I6,'UK ETS'!$A$6:$E$35,2,false) | J102: =VLOOKUP(J6,'UK ETS'!$A$6:$E$35,2,false) | K102: =VLOOKUP(K6,'UK ETS'!$A$6:$E$35,2,false) | L102: =VLOOKUP(L6,'UK ETS'!$A$6:$E$35,2,false) | M102: =VLOOKUP(M6,'UK ETS'!$A$6:$E$35,2,false) | ... Y102: =VLOOKUP(Y6,'UK ETS'!$A$6:$E$35,2,false)
B104: UK proportion of global GDP | C104: 0.032
B105: Proportion of UK GDP taxed | C105: 0.335
C106: =C105*C104
A107: HP | C107: Constants | D107: 2022 | E107: 2023 | F107: 2024 | G107: 2025 | H107: 2026 | I107: 2027 | J107: 2028 | K107: 2029 | L107: 2030 | M107: 2031 | N107: 2032 | O107: 2033 | P107: 2034 | Q107: 2035 | R107: 2036 | S107: 2037 | T107: 2038 | U107: 2039 | V107: 2040 | W107: 2041 | X107: 2042 | Y107: 2043
B108: Elec consumption change (kWh, annual) | C108: 3080 | D108: =C108 | E108: =D108 | F108: =E108 | G108: =F108 | H108: =G108 | I108: =H108 | J108: =I108 | K108: =J108 | ... Y108: =X108
B109: Gas consumption change (kWh, annual) | C109: -9350.7 | D109: =C109 | E109: =D109 | F109: =E109 | G109: =F109 | H109: =G109 | I109: =H109 | J109: =I109 | K109: =J109 | ... Y109: =X109
B110: Overall energy change (kWh, annual) | C110: -6119.8
B112: HP pre-adoption elec consumption | F112: 5062.1
B113: HP pre-adoption gas consumption | F113: 10335.7
B114: HP pre-adoption overall energy consumption | F114: 15287.2
B116: Elec "long-run marginal" carbon intensity (kg/kWh) | D116: =VLOOKUP(D6,'DESNZ elec carbon intensity'!$B$11:$F$54,2,false) | E116: =VLOOKUP(E6,'DESNZ elec carbon intensity'!$B$11:$F$54,2,false) | F116: =VLOOKUP(F6,'DESNZ elec carbon intensity'!$B$11:$F$54,2,false) | G116: =VLOOKUP(G6,'DESNZ elec carbon intensity'!$B$11:$F$54,2,false) | H116: =VLOOKUP(H6,'DESNZ elec carbon intensity'!$B$11:$F$54,2,false) | I116: =VLOOKUP(I6,'DESNZ elec carbon intensity'!$B$11:$F$54,2,false) | J116: =VLOOKUP(J6,'DESNZ elec carbon intensity'!$B$11:$F$54,2,false) | K116: =VLOOKUP(K6,'DESNZ elec carbon intensity'!$B$11:$F$54,2,false) | ... Y116: =VLOOKUP(Y6,'DESNZ elec carbon intensity'!$B$11:$F$54,2,false)
B117: Gas carbon intensity (kg/kWh) | C117: ='Defra gas and elec carbon inten'!$D$26
B119: Elec air quality / pollution costs 2023£/kWh | F119: =F122/('GDP deflator'!$I$78/'GDP deflator'!$I$79) | G119: =G122/('GDP deflator'!$I$78/'GDP deflator'!$I$79) | H119: =H122/('GDP deflator'!$I$78/'GDP deflator'!$I$79) | I119: =I122/('GDP deflator'!$I$78/'GDP deflator'!$I$79) | J119: =J122/('GDP deflator'!$I$78/'GDP deflator'!$I$79) | K119: =K122/('GDP deflator'!$I$78/'GDP deflator'!$I$79) | L119: =L122/('GDP deflator'!$I$78/'GDP deflator'!$I$79) | M119: =M122/('GDP deflator'!$I$78/'GDP deflator'!$I$79) | ... Y119: =Y122/('GDP deflator'!$I$78/'GDP deflator'!$I$79)
B120: Gas air quality / pollution costs 2023£/kWh | F120: =F123/('GDP deflator'!$I$78/'GDP deflator'!$I$79) | G120: =G123/('GDP deflator'!$I$78/'GDP deflator'!$I$79) | H120: =H123/('GDP deflator'!$I$78/'GDP deflator'!$I$79) | I120: =I123/('GDP deflator'!$I$78/'GDP deflator'!$I$79) | J120: =J123/('GDP deflator'!$I$78/'GDP deflator'!$I$79) | K120: =K123/('GDP deflator'!$I$78/'GDP deflator'!$I$79) | L120: =L123/('GDP deflator'!$I$78/'GDP deflator'!$I$79) | M120: =M123/('GDP deflator'!$I$78/'GDP deflator'!$I$79) | ... Y120: =Y123/('GDP deflator'!$I$78/'GDP deflator'!$I$79)
B122: Elec air quality / pollution costs 2022£/kWh | F122: =HLOOKUP(F$90,'Air quality'!$D$11:$CC$15,3,false)/100 | G122: =HLOOKUP(G$90,'Air quality'!$D$11:$CC$15,3,false)/100 | H122: =HLOOKUP(H$90,'Air quality'!$D$11:$CC$15,3,false)/100 | I122: =HLOOKUP(I$90,'Air quality'!$D$11:$CC$15,3,false)/100 | J122: =HLOOKUP(J$90,'Air quality'!$D$11:$CC$15,3,false)/100 | K122: =HLOOKUP(K$90,'Air quality'!$D$11:$CC$15,3,false)/100 | L122: =HLOOKUP(L$90,'Air quality'!$D$11:$CC$15,3,false)/100 | M122: =HLOOKUP(M$90,'Air quality'!$D$11:$CC$15,3,false)/100 | ... Y122: =HLOOKUP(Y$90,'Air quality'!$D$11:$CC$15,3,false)/100
B123: Gas air quality / pollution costs 2022£/kWh | F123: =HLOOKUP(F$90,'Air quality'!$D$11:$CC$15,4,false)/100 | G123: =HLOOKUP(G$90,'Air quality'!$D$11:$CC$15,4,false)/100 | H123: =HLOOKUP(H$90,'Air quality'!$D$11:$CC$15,4,false)/100 | I123: =HLOOKUP(I$90,'Air quality'!$D$11:$CC$15,4,false)/100 | J123: =HLOOKUP(J$90,'Air quality'!$D$11:$CC$15,4,false)/100 | K123: =HLOOKUP(K$90,'Air quality'!$D$11:$CC$15,4,false)/100 | L123: =HLOOKUP(L$90,'Air quality'!$D$11:$CC$15,4,false)/100 | M123: =HLOOKUP(M$90,'Air quality'!$D$11:$CC$15,4,false)/100 | ... Y123: =HLOOKUP(Y$90,'Air quality'!$D$11:$CC$15,4,false)/100
B125: Private cost HP | F125: =average('MCS cost data'!C50:C57)-F126
B126: Subsidy HP (BUS £ per ASHP) | F126: 7500
B127: Private cost gas boiler | F127: 2250
B128: Implied ex-VAT cost of gas boiler | F128: =F127/1.2
B130: Average elec unit rate (Octo) | F130: 0.24499 | G130: =F130 | H130: =G130 | I130: =H130 | J130: =I130 | K130: =J130 | L130: =K130 | M130: =L130 | N130: =M130 | ... Y130: =X130
B131: Average elec standing charge (Octo) | F131: 0.5803 | G131: =F131 | H131: =G131 | I131: =H131 | J131: =I131 | K131: =J131 | L131: =K131 | M131: =L131 | N131: =M131 | ... Y131: =X131
B132: Average gas unit rate (Octo) | F132: 0.06041 | G132: =F132 | H132: =G132 | I132: =H132 | J132: =I132 | K132: =J132 | L132: =K132 | M132: =L132 | N132: =M132 | ... Y132: =X132
B133: Average gas standing charge (Octo) | F133: 0.2936 | G133: =F133 | H133: =G133 | I133: =H133 | J133: =I133 | K133: =J133 | L133: =K133 | M133: =L133 | N133: =M133 | ... Y133: =X133
B134: Elec unit rate (HMG forecast) (£2023) | F134: =F136/('GDP deflator'!$I$78/'GDP deflator'!$I$79) | G134: =G136/('GDP deflator'!$I$78/'GDP deflator'!$I$79) | H134: =H136/('GDP deflator'!$I$78/'GDP deflator'!$I$79) | I134: =I136/('GDP deflator'!$I$78/'GDP deflator'!$I$79) | J134: =J136/('GDP deflator'!$I$78/'GDP deflator'!$I$79) | K134: =K136/('GDP deflator'!$I$78/'GDP deflator'!$I$79) | L134: =L136/('GDP deflator'!$I$78/'GDP deflator'!$I$79) | M134: =M136/('GDP deflator'!$I$78/'GDP deflator'!$I$79) | ... Y134: =Y136/('GDP deflator'!$I$78/'GDP deflator'!$I$79)
...

Sheet GDP deflator
A1: Source: https://www.gov.uk/government/collections/gdp-deflators-at-market-prices-and-money-gdp#:~:text=GDP%20deflators%20at%20market%20prices%2C%20and%20money%20GDP%20June%202024%20(Quarterly%20National%20Accounts)
B4: GDP DEFLATORS AT MARKET PRICES, AND MONEY GDP
B6: Outturn data are as at the Quarterly National Accounts from ONS - last updated 28 June 2024.
B7: Forecast data are consistent with OBR EFO data as at Budget 6 March 2024.
B8: Financial year | H8: Calendar year
C9: GDP deflator at market prices | E9: Money GDP (3), (4) | I9: GDP deflator at market prices | K9: Money GDP (3)
B10: Financial year | C10: 2023-24 = 100 | D10: per cent change on previous year | E10: Cash £ million Non-Season-ally Adjusted | F10: Cash £ million Seasonally Adjusted | H10: Calendar year | I10: 2023 = 100 | J10: per cent change on previous year | K10: Cash £ million Non-Seasonally Adjusted
B11: 1955-56 | C11: 3.316 | E11: 19574 | F11: 19589 | H11: 1955 | I11: 3.3 | K11: 19169
B12: 1956-57 | C12: 3.522 | D12: 6.21 | E12: 21162 | F12: 21138 | H12: 1956 | I12: 3.53 | J12: 6.94 | K12: 20844
B13: 1957-58 | C13: 3.684 | D13: 4.61 | E13: 22509 | F13: 22524 | H13: 1957 | I13: 3.671 | J13: 4.01 | K13: 22104
B14: 1958-59 | C14: 3.774 | D14: 2.43 | E14: 23335 | F14: 23305 | H14: 1958 | I14: 3.805 | J14: 3.65 | K14: 23220
B15: 1959-60 | C15: 3.794 | D15: 0.52 | E15: 24873 | F15: 24928 | H15: 1959 | I15: 3.832 | J15: 0.72 | K15: 24388
B16: 1960-61 | C16: 3.869 | D16: 2 | E16: 26639 | F16: 26657 | H16: 1960 | I16: 3.872 | J16: 1.04 | K16: 26201
B17: 1961-62 | C17: 4.012 | D17: 3.67 | E17: 28141 | F17: 28169 | H17: 1961 | I17: 4.019 | J17: 3.79 | K17: 27918
B18: 1962-63 | C18: 4.137 | D18: 3.12 | E18: 29450 | F18: 29468 | H18: 1962 | I18: 4.164 | J18: 3.6 | K18: 29235
B19: 1963-64 | C19: 4.206 | D19: 1.68 | E19: 31921 | F19: 31876 | H19: 1963 | I19: 4.225 | J19: 1.46 | K19: 31099
B20: 1964-65 | C20: 4.404 | D20: 4.71 | E20: 34855 | F20: 34924 | H20: 1964 | I20: 4.376 | J20: 3.58 | K20: 34047
B21: 1965-66 | C21: 4.641 | D21: 5.38 | E21: 37461 | F21: 37415 | H21: 1965 | I21: 4.636 | J21: 5.94 | K21: 36828
B22: 1966-67 | C22: 4.877 | D22: 5.09 | E22: 39949 | F22: 39946 | H22: 1966 | I22: 4.883 | J22: 5.34 | K22: 39394
B23: 1967-68 | C23: 5.011 | D23: 2.74 | E23: 42504 | F23: 42612 | H23: 1967 | I23: 5.027 | J23: 2.94 | K23: 41673
... B55: 1999-00 | C55: 56.386 | D55: 1.33 | E55: 1058069 | F55: 1059608 | H55: 1999 | I55: 56.767 | J55: 1.37 | K55: 1043248
B56: 36526 | C56: 56.961 | D56: 1.02 | E56: 1114639 | F56: 1111547 | H56: 2000 | I56: 57.418 | J56: 1.15 | K56: 1100752
B57: 36923 | C57: 57.928 | D57: 1.7 | E57: 1152363 | F57: 1155639 | H57: 2001 | I57: 58.283 | J57: 1.51 | K57: 1146135
B58: 37316 | C58: 59.244 | D58: 2.27 | E58: 1208864 | F58: 1206462 | H58: 2002 | I58: 59.517 | J58: 2.12 | K58: 1191439
B59: 37712 | C59: 60.591 | D59: 2.27 | E59: 1272601 | F59: 1273669 | H59: 2003 | I59: 60.941 | J59: 2.39 | K59: 1258334
B60: 38108 | C60: 62.411 | D60: 3 | E60: 1342153 | F60: 1341238 | H60: 2004 | I60: 62.537 | J60: 2.62 | K60: 1322637
B61: 38504 | C61: 64.119 | D61: 2.74 | E61: 1418417 | F61: 1418626 | H61: 2005 | I61: 64.373 | J61: 2.94 | K61: 1398749
B62: 38899 | C62: 65.833 | D62: 2.67 | E62: 1486255 | F62: 1487819 | H62: 2006 | I62: 66.169 | J62: 2.79 | K62: 1472038
B63: 39295 | C63: 67.426 | D63: 2.42 | E63: 1565822 | F63: 1565136 | H63: 2007 | I63: 67.658 | J63: 2.25 | K63: 1544637
B64: 39692 | C64: 69.854 | D64: 3.6 | E64: 1582979 | F64: 1582791 | H64: 2008 | I64: 69.979 | J64: 3.43 | K64: 1593600
B65: 40087 | C65: 70.799 | D65: 1.35 | E65: 1557028 | F65: 1558176 | H65: 2009 | I65: 71.288 | J65: 1.87 | K65: 1548802
B66: 40483 | C66: 72.133 | D66: 1.88 | E66: 1627823 | F66: 1627172 | H66: 2010 | I66: 72.415 | J66: 1.58 | K66: 1608553
B67: 40878 | C67: 73.405 | D67: 1.76 | E67: 1673244 | F67: 1672562 | H67: 2011 | I67: 74.001 | J67: 2.19 | K67: 1662590
B68: 2012-13 | C68: 74.752 | D68: 1.84 | E68: 1725339 | F68: 1727114 | H68: 2012 | I68: 75.139 | J68: 1.54 | K68: 1713715
B69: 2013-14 | C69: 76.189 | D69: 1.92 | E69: 1803853 | F69: 1801250 | H69: 2013 | I69: 76.729 | J69: 2.12 | K69: 1781361
B70: 2014-15 | C70: 77.116 | D70: 1.22 | E70: 1875404 | F70: 1879260 | H70: 2014 | I70: 77.74 | J70: 1.32 | K70: 1862514
B71: 2015-16 | C71: 77.671 | D71: 0.72 | E71: 1932100 | F71: 1931443 | H71: 2015 | I71: 78.255 | J71: 0.66 | K71: 1916451
B72: 2016-17 | C72: 79.438 | D72: 2.27 | E72: 2013605 | F72: 2015841 | H72: 2016 | I72: 79.791 | J72: 1.96 | K72: 1991645
B73: 2017-18 | C73: 80.682 | D73: 1.57 | E73: 2098808 | F73: 2099822 | H73: 2017 | I73: 81.273 | J73: 1.86 | K73: 2082482
B74: 2018-19 | C74: 82.384 | D74: 2.11 | E74: 2173677 | F74: 2170432 | H74: 2018 | I74: 82.836 | J74: 1.92 | K74: 2152304
B75: 2019-20 | C75: 84.329 | D75: 2.36 | E75: 2244509 | F75: 2240706 | H75: 2019 | I75: 84.588 | J75: 2.11 | K75: 2233921
B76: 2020-21 | C76: 88.921 | D76: 5.45 | E76: 2085084 | F76: 2086121 | H76: 2020 | I76: 89.074 | J76: 5.3 | K76: 2104288
B77: 2021-22 | C77: 88.192 | D77: -0.82 | E77: 2361920 | F77: 2354396 | H77: 2021 | I77: 88.789 | J77: -0.32 | K77: 2284079
B78: 2022-23 | C78: 94.134 | D78: 6.74 | E78: 2553253 | F78: 2555445 | H78: 2022 | I78: 93.352 | J78: 5.14 | K78: 2505981
B79: 2023-24 | C79: 100 | D79: 6.23 | E79: 2720272 | F79: 2717531 | H79: 2023 | I79: 100 | J79: 7.12 | K79: 2687186
B80: 2024-25 (1), (2) | C80: - | D80: 0.8 | E80: 2785614 | F80: 2784209 | H80: 2024 (1), (2) | I80: - | J80: 1.52 | K80: 2766360
B81: 2025-26 (1), (2) | C81: - | D81: 1.35 | E81: 2875062 | F81: 2876148 | H81: 2025 (1), (2) | I81: - | J81: 1.18 | K81: 2850872
B82: 2026-27 (1), (2) | C82: - | D82: 1.74 | E82: 2984832 | F82: 2984381 | H82: 2026 (1), (2) | I82: - | J82: 1.67 | K82: 2956987
B83: 2027-28 (1), (2) | C83: - | D83: 1.87 | E83: 3094490 | F83: 3094490 | H83: 2027 (1), (2) | I83: - | J83: 1.85 | K83: 3066787
B84: 2028-29 (1), (2) | C84: - | D84: 1.93 | E84: 3207476 | F84: 3207476 | H84: 2028 (1), (2) | I84: - | J84: 1.92 | K84: 3178873
B85: Sources and footnotes:
B86: GDP Deflator: | C86: Financial years 1955-56 to 2023-24 taken from ONS series L8GG in data tables: Table N.
C87: https://www.ons.gov.uk/file?uri=/economy/grossdomesticproductgdp/datasets/uksecondestimateofgdpdatatables/quarter1jantomar2024quarterlynationalaccounts/quarterlynationalaccountsdatatables.xlsx
C88: Calendar years 1955 to 2023 taken from ONS series MNF2 in data tables: Table O.
C89: https://www.ons.gov.uk/file?uri=/economy/grossdomesticproductgdp/datasets/uksecondestimateofgdpdatatables/quarter1jantomar2024quarterlynationalaccounts/quarterlynationalaccountsdatatables.xlsx
C90: For years 2024-25 to 2028-29 (2024 to 2028): taken from the Office for Budget Responsibility (OBR) GDP deflator forecasts as of March 2024 EFO detailed forecast tables.
C91: https://obr.uk/efo/economic-and-fiscal-outlook-march-2024/
B92: Money GDP: | C92: For years 1955-56 to 2023-24 (1955 to 2023): ONS data for money GDP not seasonally adjusted series BKTL in data tables: Table N.
C93: https://www.ons.gov.uk/file?uri=/economy/grossdomesticproductgdp/datasets/uksecondestimateofgdpdatatables/quarter1jantomar2024quarterlynationalaccounts/quarterlynationalaccountsdatatables.xlsx
C94: For years 1955-56 to 2023-24: ONS data for money GDP seasonally adjusted series YBHA in data tables: Table N.
C95: https://www.ons.gov.uk/file?uri=/economy/grossdomesticproductgdp/datasets/uksecondestimateofgdpdatatables/quarter1jantomar2024quarterlynationalaccounts/quarterlynationalaccountsdatatables.xlsx
C96: For years 2024-25 to 2028-29 (2024 to 2028): taken from the Office for Budget Responsibility (OBR) GDP deflator forecasts as of March 2024 EFO detailed forecast tables.
C97: https://obr.uk/efo/economic-and-fiscal-outlook-march-2024/
B98: Footnotes:
B99: -1 | C99: For years 2024-25 to 2028-29 (2024 to 2028), this presentation only shows percentage changes in line with data taken from the OBR GDP deflator forecasts as of March 2024 EFO detailed forecast tables.
B100: -2 | C100: For years 2024-25 to 2028-29 (2024 to 2028), money GDP forecasts from the OBR as of the Budget, March 2024.
B101: -3 | C101: Non-Seasonally adjusted money GDP (BKTL) from 1955-56 to 2023-24 (1955 to 2023) consistent with ONS Quarterly National Accounts release of 28 June 2024.
B102: -4 | C102: Seasonally adjusted money GDP (YBHA) from 1955-56 to 2022-23 consistent with ONS Quarterly National Accounts release of 28 June 2024.
B103: -5 | C103: For further information and the 'User's Guide' to these series, please visit the following page on the GOV.UK website at:
C104: https://www.gov.uk/government/publications/gross-domestic-product-gdp-deflators-user-guide
B105: -6 | C105: For practical examples of how to use the GDP deflator series, please visit the following page on the GOV.UK website at:
C106: https://www.gov.uk/government/publications/how-to-use-the-gdp-deflator-series-practical-examples

Sheet Defra gas and elec carbon inten
A1: Source: https://www.gov.uk/government/publications/greenhouse-gas-reporting-conversion-factors-2023
A4: Activity | B4: Country | C4: Unit | D4: Year | E4: kg CO2e | F4: kg CO2e of CO2 per unit | G4: kg CO2e of CH4 per unit | H4: kg CO2e of N2O per unit
A5: Electricity generated | B5: Electricity: UK | C5: kWh | D5: 2023 | E5: 0.207074 | F5: 0.20496 | G5: 0.000896 | H5: 0.001218
A7: Activity | B7: Fuel | C7: Unit | D7: kg CO2e | E7: kg CO2e of CO2 per unit | F7: kg CO2e of CH4 per unit | G7: kg CO2e of N2O per unit
A8: Gaseous fuels | B8: Butane | C8: tonnes | D8: 3033.38 | E8: 3029.26 | F8: 2.52 | G8: 1.6
C9: litres | D9: 1.75 | E9: 1.74 | F9: 0 | G9: 0
C10: kWh (Net CV) | D10: 0.24 | E10: 0.24 | F10: 0 | G10: 0
C11: kWh (Gross CV) | D11: 0.22 | E11: 0.22 | F11: 0 | G11: 0
B12: CNG | C12: tonnes | D12: 2562.57 | E12: 2557.53 | F12: 3.85 | G12: 1.19
C13: litres | D13: 0.45 | E13: 0.44757 | F13: 0.00067 | G13: 0.0002
C14: kWh (Net CV) | D14: 0.2 | E14: 0.20226 | F14: 0.00031 | G14: 0.0001
C15: kWh (Gross CV) | D15: 0.18 | E15: 0.18256 | F15: 0.00028 | G15: 9e-05
B16: LNG | C16: tonnes | D16: 2581.98 | E16: 2576.94 | F16: 3.85 | G16: 1.19
C17: litres | D17: 1.17 | E17: 1.16604 | F17: 0.00175 | G17: 0.00054
C18: kWh (Net CV) | D18: 0.2 | E18: 0.20379 | F18: 0.00031 | G18: 0.0001
C19: kWh (Gross CV) | D19: 0.18 | E19: 0.18395 | F19: 0.00028 | G19: 9e-05
B20: LPG | C20: tonnes | D20: 2939.36 | E20: 2935.18 | F20: 2.55 | G20: 1.63
C21: litres | D21: 1.56 | E21: 1.55491 | F21: 0.00136 | G21: 0.00086
C22: kWh (Net CV) | D22: 0.23 | E22: 0.22999 | F22: 0.0002 | G22: 0.00012
C23: kWh (Gross CV) | D23: 0.21 | E23: 0.21419 | F23: 0.00019 | G23: 0.00012
B24: Natural gas | C24: tonnes | D24: 2562.57 | E24: 2557.53 | F24: 3.85 | G24: 1.19
C25: cubic metres | D25: 2.04 | E25: 2.03437 | F25: 0.00307 | G25: 0.00095
C26: kWh (Net CV) | D26: 0.2 | E26: 0.20226 | F26: 0.00031 | G26: 0.0001
C27: kWh (Gross CV) | D27: 0.18 | E27: 0.18256 | F27: 0.00028 | G27: 9e-05
B28: Natural gas (100% mineral blend) | C28: tonnes | D28: 2581.98 | E28: 2576.94 | F28: 3.85 | G28: 1.19
C29: cubic metres | D29: 2.05 | E29: 2.04981 | F29: 0.00307 | G29: 0.00095
C30: kWh (Net CV) | D30: 0.2 | E30: 0.20379 | F30: 0.00031 | G30: 0.0001
C31: kWh (Gross CV) | D31: 0.18 | E31: 0.18395 | F31: 0.00028 | G31: 9e-05
B32: Other petroleum gas | C32: tonnes | D32: 2578.25 | E32: 2575.7 | F32: 1.31 | G32: 1.24
C33: litres | D33: 0.94 | E33: 0.94348 | F33: 0.00048 | G33: 0.00045
C34: kWh (Net CV) | D34: 0.2 | E34: 0.19897 | F34: 0.0001 | G34: 0.0001
C35: kWh (Gross CV) | D35: 0.18 | E35: 0.18305 | F35: 9e-05 | G35: 9e-05
B36: Propane | C36: tonnes | D36: 2997.63 | E36: 2993.4 | F36: 2.5872 | G36: 1.64513
C37: litres | D37: 1.54 | E37: 1.5414 | F37: 0.00133 | G37: 0.00084
C38: kWh (Net CV) | D38: 0.23 | E38: 0.23225 | F38: 0.0002 | G38: 0.00012
C39: kWh (Gross CV) | D39: 0.21 | E39: 0.21381 | F39: 0.00018 | G39: 0.00012

Sheet Retail energy prices forecast
A1: Source: https://assets.publishing.service.gov.uk/media/6567994fcc1ec5000d8eef17/data-tables-1-19.xlsx
B3: Tables 4-8: Retail prices
B5: We strongly advise the use of the full range of prices in all analysis due to the current uncertainty in energy prices, especially where the level of price has a material impact on your outcomes. This is due to the significant uncertainties across all components of prices, as observed from historic and current volatility, and in the transition to Net Zero.
C7: Table 4 - Retail Electricity Prices (real 2022 p/kWh) | M7: Table 5 - Retail Gas Prices (real 2022 p/kWh) | W7: Table 6 - Retail Coal Prices (real 2022 p/kWh) | AG7: Table 7 - Retail Oil Prices (real 2022 p/litre) | AQ7: Table 8 - Retail Road Fuel Prices (real 2022 p/litre)
C8: Low | F8: Central | I8: High | M8: Low | P8: Central | S8: High | W8: Low | Z8: Central | AC8: High | AG8: Low | AJ8: Central | AM8: High | AQ8: Low | AS8: Central | AU8: High
B9: Year | C9: Domestic | D9: Commercial/ Public sector | E9: Industrial | F9: Domestic | G9: Commercial/ Public sector | H9: Industrial | I9: Domestic | J9: Commercial/ Public sector | K9: Industrial | M9: Domestic | N9: Commercial/ Public sector | O9: Industrial | P9: Domestic | Q9: Commercial/ Public sector | R9: Industrial | S9: Domestic | T9: Commercial/ Public sector | U9: Industrial | W9: Domestic | X9: Commercial/ Public sector | Y9: Industrial | Z9: Domestic | AA9: Commercial/ Public sector | AB9: Industrial | AC9: Domestic | AD9: Commercial/ Public sector | AE9: Industrial | AG9: Domestic | AH9: Commercial/ Public sector | AI9: Industrial | AJ9: Domestic | AK9: Commercial/ Public sector | AL9: Industrial | AM9: Domestic | AN9: Commercial/ Public sector | AO9: Industrial | AQ9: Petrol (weighted average) | AR9: DERV | AS9: Petrol (weighted average) | AT9: DERV | AU9: Petrol (weighted average) | AV9: DERV
B10: 2010 | C10: 16.06 | D10: 10.62 | E10: 8.86 | F10: 16.06 | G10: 10.62 | H10: 8.86 | I10: 16.06 | J10: 10.62 | K10: 8.86 | M10: 4.77 | N10: 2.82 | O10: 2.12 | P10: 4.77 | Q10: 2.82 | R10: 2.12 | S10: 4.77 | T10: 2.82 | U10: 2.12 | W10: 6.76 | X10: 1.58 | Y10: 1.21 | Z10: 6.76 | AA10: 1.58 | AB10: 1.21 | AC10: 6.76 | AD10: 1.58 | AE10: 1.21 | AG10: 59.1 | AH10: 68.8 | AI10: 65.8 | AJ10: 59.1 | AK10: 68.8 | AL10: 65.8 | AM10: 59.1 | AN10: 68.8 | AO10: 65.8 | AQ10: 152.4 | AR10: 155.1 | AS10: 152.4 | AT10: 155.1 | AU10: 152.4 | AV10: 155.1
B11: 2011 | C11: 17.11 | D11: 11.08 | E11: 9.19 | F11: 17.11 | G11: 11.08 | H11: 9.19 | I11: 17.11 | J11: 11.08 | K11: 9.19 | M11: 5.3 | N11: 3.21 | O11: 2.68 | P11: 5.3 | Q11: 3.21 | R11: 2.68 | S11: 5.3 | T11: 3.21 | U11: 2.68 | W11: 6.94 | X11: 1.72 | Y11: 1.32 | Z11: 6.94 | AA11: 1.72 | AB11: 1.32 | AC11: 6.94 | AD11: 1.72 | AE11: 1.32 | AG11: 74 | AH11: 83.3 | AI11: 80.3 | AJ11: 74 | AK11: 83.3 | AL11: 80.3 | AM11: 74 | AN11: 83.3 | AO11: 80.3 | AQ11: 169.9 | AR11: 176.5 | AS11: 169.9 | AT11: 176.5 | AU11: 169.9 | AV11: 176.5
B12: 2012 | C12: 17.78 | D12: 11.79 | E12: 10.05 | F12: 17.78 | G12: 11.79 | H12: 10.05 | I12: 17.78 | J12: 11.79 | K12: 10.05 | M12: 5.7 | N12: 3.71 | O12: 2.77 | P12: 5.7 | Q12: 3.71 | R12: 2.77 | S12: 5.7 | T12: 3.71 | U12: 2.77 | W12: 7.08 | X12: 1.66 | Y12: 1.27 | Z12: 7.08 | AA12: 1.66 | AB12: 1.27 | AC12: 7.08 | AD12: 1.66 | AE12: 1.27 | AG12: 74.3 | AH12: 86.3 | AI12: 82.2 | AJ12: 74.3 | AK12: 86.3 | AL12: 82.2 | AM12: 74.3 | AN12: 86.3 | AO12: 82.2 | AQ12: 170 | AR12: 177.8 | AS12: 170 | AT12: 177.8 | AU12: 170 | AV12: 177.8
B13: 2013 | C13: 18.58 | D13: 12.34 | E13: 11 | F13: 18.58 | G13: 12.34 | H13: 11 | I13: 18.58 | J13: 12.34 | K13: 11 | M13: 5.94 | N13: 4.03 | O13: 2.91 | P13: 5.94 | Q13: 4.03 | R13: 2.91 | S13: 5.94 | T13: 4.03 | U13: 2.91 | W13: 7.04 | X13: 1.71 | Y13: 1.31 | Z13: 7.04 | AA13: 1.71 | AB13: 1.31 | AC13: 7.04 | AD13: 1.71 | AE13: 1.31 | AG13: 70.1 | AH13: 83.8 | AI13: 78.7 | AJ13: 70.1 | AK13: 83.8 | AL13: 78.7 | AM13: 70.1 | AN13: 83.8 | AO13: 78.7 | AQ13: 165.1 | AR13: 172.3 | AS13: 165.1 | AT13: 172.3 | AU13: 165.1 | AV13: 172.3
B14: 2014 | C14: 19.29 | D14: 12.96 | E14: 11.2 | F14: 19.29 | G14: 12.96 | H14: 11.2 | I14: 19.29 | J14: 12.96 | K14: 11.2 | M14: 6.23 | N14: 3.94 | O14: 2.59 | P14: 6.23 | Q14: 3.94 | R14: 2.59 | S14: 6.23 | T14: 3.94 | U14: 2.59 | W14: 7.14 | X14: 1.69 | Y14: 1.29 | Z14: 7.14 | AA14: 1.69 | AB14: 1.29 | AC14: 7.14 | AD14: 1.69 | AE14: 1.29 | AG14: 60.8 | AH14: 77.1 | AI14: 70.5 | AJ14: 60.8 | AK14: 77.1 | AL14: 70.5 | AM14: 60.8 | AN14: 77.1 | AO14: 70.5 | AQ14: 154.9 | AR14: 161.7 | AS14: 154.9 | AT14: 161.7 | AU14: 154.9 | AV14: 161.7
B15: 2015 | C15: 18.92 | D15: 13.38 | E15: 11.3 | F15: 18.92 | G15: 13.38 | H15: 11.3 | I15: 18.92 | J15: 13.38 | K15: 11.3 | M15: 5.85 | N15: 3.54 | O15: 2.23 | P15: 5.85 | Q15: 3.54 | R15: 2.23 | S15: 5.85 | T15: 3.54 | U15: 2.23 | W15: 7.11 | X15: 1.48 | Y15: 1.13 | Z15: 7.11 | AA15: 1.48 | AB15: 1.13 | AC15: 7.11 | AD15: 1.48 | AE15: 1.13 | AG15: 41 | AH15: 56.5 | AI15: 52 | AJ15: 41 | AK15: 56.5 | AL15: 52 | AM15: 41 | AN15: 56.5 | AO15: 52 | AQ15: 134.2 | AR15: 138.3 | AS15: 134.2 | AT15: 138.3 | AU15: 134.2 | AV15: 138.3
B16: 2016 | C16: 18.3 | D16: 12.87 | E16: 11.06 | F16: 18.3 | G16: 12.87 | H16: 11.06 | I16: 18.3 | J16: 12.87 | K16: 11.06 | M16: 5.23 | N16: 3.06 | O16: 1.76 | P16: 5.23 | Q16: 3.06 | R16: 1.76 | S16: 5.23 | T16: 3.06 | U16: 1.76 | W16: 6.96 | X16: 1.35 | Y16: 1.04 | Z16: 6.96 | AA16: 1.35 | AB16: 1.04 | AC16: 6.96 | AD16: 1.35 | AE16: 1.04 | AG16: 36 | AH16: 49.6 | AI16: 47.9 | AJ16: 36 | AK16: 49.6 | AL16: 47.9 | AM16: 36 | AN16: 49.6 | AO16: 47.9 | AQ16: 129 | AR16: 130 | AS16: 129 | AT16: 130 | AU16: 129 | AV16: 130
B17: 2017 | C17: 19.21 | D17: 13.15 | E17: 11.51 | F17: 19.21 | G17: 13.15 | H17: 11.51 | I17: 19.21 | J17: 13.15 | K17: 11.51 | M17: 5.03 | N17: 2.88 | O17: 1.83 | P17: 5.03 | Q17: 2.88 | R17: 1.83 | S17: 5.03 | T17: 2.88 | U17: 1.83 | W17: 6.99 | X17: 1.5 | Y17: 1.15 | Z17: 6.99 | AA17: 1.5 | AB17: 1.15 | AC17: 6.99 | AD17: 1.5 | AE17: 1.15 | AG17: 45.4 | AH17: 57.7 | AI17: 55.6 | AJ17: 45.4 | AK17: 57.7 | AL17: 55.6 | AM17: 45.4 | AN17: 57.7 | AO17: 55.6 | AQ17: 136.9 | AR17: 139.4 | AS17: 136.9 | AT17: 139.4 | AU17: 136.9 | AV17: 139.4
B18: 2018 | C18: 20.46 | D18: 14.02 | E18: 11.5 | F18: 20.46 | G18: 14.02 | H18: 11.5 | I18: 20.46 | J18: 14.02 | K18: 11.5 | M18: 5.03 | N18: 3.17 | O18: 2.2 | P18: 5.03 | Q18: 3.17 | R18: 2.2 | S18: 5.03 | T18: 3.17 | U18: 2.2 | W18: 6.99 | X18: 1.82 | Y18: 1.39 | Z18: 6.99 | AA18: 1.82 | AB18: 1.39 | AC18: 6.99 | AD18: 1.82 | AE18: 1.39 | AG18: 55 | AH18: 65.7 | AI18: 63.3 | AJ18: 55 | AK18: 65.7 | AL18: 63.3 | AM18: 55 | AN18: 65.7 | AO18: 63.3 | AQ18: 143.4 | AR18: 148.3 | AS18: 143.4 | AT18: 148.3 | AU18: 143.4 | AV18: 148.3
B19: 2019 | C19: 21.9 | D19: 14.31 | E19: 12.47 | F19: 21.9 | G19: 14.31 | H19: 12.47 | I19: 21.9 | J19: 14.31 | K19: 12.47 | M19: 5.11 | N19: 2.96 | O19: 1.95 | P19: 5.11 | Q19: 2.96 | R19: 1.95 | S19: 5.11 | T19: 2.96 | U19: 1.95 | W19: 7.1 | X19: 1.75 | Y19: 1.34 | Z19: 7.1 | AA19: 1.75 | AB19: 1.34 | AC19: 7.1 | AD19: 1.75 | AE19: 1.34 | AG19: 52.4 | AH19: 64.6 | AI19: 59.2 | AJ19: 52.4 | AK19: 64.6 | AL19: 59.2 | AM19: 52.4 | AN19: 64.6 | AO19: 59.2 | AQ19: 140.1 | AR19: 146.9 | AS19: 140.1 | AT19: 146.9 | AU19: 140.1 | AV19: 146.9
B20: 2020 | C20: 20.72 | D20: 14.03 | E20: 12.26 | F20: 20.72 | G20: 14.03 | H20: 12.26 | I20: 20.72 | J20: 14.03 | K20: 12.26 | M20: 4.59 | N20: 2.66 | O20: 1.68 | P20: 4.59 | Q20: 2.66 | R20: 1.68 | S20: 4.59 | T20: 2.66 | U20: 1.68 | W20: 6.99 | X20: 1.4 | Y20: 1.07 | Z20: 6.99 | AA20: 1.4 | AB20: 1.07 | AC20: 6.99 | AD20: 1.4 | AE20: 1.07 | AG20: 31.2 | AH20: 57.3 | AI20: 45.8 | AJ20: 31.2 | AK20: 57.3 | AL20: 45.8 | AM20: 31.2 | AN20: 57.3 | AO20: 45.8 | AQ20: 120.8 | AR20: 125.7 | AS20: 120.8 | AT20: 125.7 | AU20: 120.8 | AV20: 125.7
B21: 2021 | C21: 22.59 | D21: 15.16 | E21: 14.04 | F21: 22.59 | G21: 15.16 | H21: 14.04 | I21: 22.59 | J21: 15.16 | K21: 14.04 | M21: 4.4 | N21: 3.44 | O21: 2.84 | P21: 4.4 | Q21: 3.44 | R21: 2.84 | S21: 4.4 | T21: 3.44 | U21: 2.84 | W21: 7.21 | X21: 1.54 | Y21: 1.18 | Z21: 7.21 | AA21: 1.54 | AB21: 1.18 | AC21: 7.21 | AD21: 1.54 | AE21: 1.18 | AG21: 45.1 | AH21: 59.5 | AI21: 50.7 | AJ21: 45.1 | AK21: 59.5 | AL21: 50.7 | AM21: 45.1 | AN21: 59.5 | AO21: 50.7 | AQ21: 139 | AR21: 142.2 | AS21: 139 | AT21: 142.2 | AU21: 139 | AV21: 142.2
... B100: 2100 | C100: 19.1 | D100: 11.59 | E100: 10.26 | F100: 20.3 | G100: 12.11 | H100: 11.4 | I100: 21.56 | J100: 13.05 | K100: 13.04 | M100: 3.78 | N100: 2.11 | O100: 1.18 | P100: 5.52 | Q100: 3.81 | R100: 2.89 | S100: 8.6 | T100: 6.82 | U100: 5.93 | W100: 7.63 | X100: 2.42 | Y100: 1.74 | Z100: 8.44 | AA100: 3.04 | AB100: 2.36 | AC100: 8.44 | AD100: 3.04 | AE100: 2.36 | AG100: 24.5 | AH100: 38.8 | AI100: 28.9 | AJ100: 49.2 | AK100: 62.8 | AL100: 52.9 | AM100: 98.6 | AN100: 110.8 | AO100: 100.9 | AQ100: 97 | AR100: 97.7 | AS100: 126.8 | AT100: 127.9 | AU100: 186.3 | AV100: 188.3
B102: Note 1: Non-domestic prices are inclusive of Climate Change Levy | AQ102: Notes:
B103: Note 2: The retail prices/long run variable costs for gas are based on internal DESNZmodelling including the fossil fuel price assumptions, where more information can be found at https://www.gov.uk/government/collections/fossil-fuel-price-assumptions. | AQ103: Petrol comprises a weighted average of Super and Premium unleaded
B106: Further guidance on the use of retail prices is available from the appraisal guidance (Chapter 3). Details on the components of the retail price can be found in the background documentation (Chapter 5). These documents can be downloaded from the Green Gook supplementary guidance section of GOV.UK webpage:
B107: https://www.gov.uk/government/publications/valuation-of-energy-use-and-greenhouse-gas-emissions-for-appraisal

Sheet SCC HMG
A1: Source: https://www.gov.uk/government/publications/valuing-greenhouse-gas-emissions-in-policy-appraisal/valuation-of-greenhouse-gas-emissions-for-policy-appraisal-and-evaluation
A4: Year | B4: Low series | C4: Central Series | D4: High Series
A5: 2020 | B5: 120 | C5: 241 | D5: 361
A6: 2021 | B6: 122 | C6: 245 | D6: 367
A7: 2022 | B7: 124 | C7: 248 | D7: 373
A8: 2023 | B8: 126 | C8: 252 | D8: 378
A9: 2024 | B9: 128 | C9: 256 | D9: 384
A10: 2025 | B10: 130 | C10: 260 | D10: 390
A11: 2026 | B11: 132 | C11: 264 | D11: 396
A12: 2027 | B12: 134 | C12: 268 | D12: 402
A13: 2028 | B13: 136 | C13: 272 | D13: 408
A14: 2029 | B14: 138 | C14: 276 | D14: 414
A15: 2030 | B15: 140 | C15: 280 | D15: 420
A16: 2031 | B16: 142 | C16: 285 | D16: 427
... A35: 2050 | B35: 189 | C35: 378 | D35: 568

Sheet SCC IWG
A1: Source: https://bidenwhitehouse.archives.gov/omb/information-regulatory-affairs/regulatory-matters/#scghgs Social Cost of Greenhouse Gases Annual Values (February 26, 2021)
B3: year | C3: 5.0%_CO2 | D3: 3.0%_CO2 | E3: 2.5%_CO2 | F3: 3% 95th Pct._CO2 | G3: 5.0%_CH4 | H3: 3.0%_CH4 | I3: 2.5%_CH4 | J3: 3% 95th Pct._CH4 | K3: 5.0%_N2O | L3: 3.0%_N2O | M3: 2.5%_N2O | N3: 3% 95th Pct._N2O
B4: 2020 | C4: 14.476 | D4: 51.082 | E4: 76.421 | F4: 151.608 | G4: 665.688 | H4: 1485.078 | I4: 1953.209 | J4: 3906.371 | K4: 5779.426 | L4: 18405.298 | M4: 27130.806 | N4: 48255.974
B5: 2021 | C5: 14.964 | D5: 52.15 | E5: 77.727 | F5: 155.119 | G5: 692.917 | H5: 1532.015 | I5: 2008.649 | J5: 4034.779 | K5: 5981.4 | L5: 18842.379 | M5: 27687.532 | N5: 49463.691
B6: 2022 | C6: 15.453 | D6: 53.219 | E6: 79.033 | F6: 158.629 | G6: 720.147 | H6: 1578.952 | I6: 2064.09 | J6: 4163.187 | K6: 6183.373 | L6: 19279.46 | M6: 28244.259 | N6: 50671.409
B7: 2023 | C7: 15.942 | D7: 54.287 | E7: 80.339 | F7: 162.139 | G7: 747.376 | H7: 1625.89 | I7: 2119.53 | J7: 4291.595 | K7: 6385.347 | L7: 19716.542 | M7: 28800.985 | N7: 51879.127
B8: 2024 | C8: 16.431 | D8: 55.355 | E8: 81.645 | F8: 165.65 | G8: 774.605 | H8: 1672.827 | I8: 2174.97 | J8: 4420.003 | K8: 6587.321 | L8: 20153.623 | M8: 29357.712 | N8: 53086.844
B9: 2025 | C9: 16.919 | D9: 56.423 | E9: 82.951 | F9: 169.16 | G9: 801.834 | H9: 1719.764 | I9: 2230.41 | J9: 4548.41 | K9: 6789.294 | L9: 20590.704 | M9: 29914.439 | N9: 54294.562
B10: 2026 | C10: 17.408 | D10: 57.491 | E10: 84.257 | F10: 172.67 | G10: 829.063 | H10: 1766.701 | I10: 2285.851 | J10: 4676.818 | K10: 6991.268 | L10: 21027.785 | M10: 30471.165 | N10: 55502.279
B11: 2027 | C11: 17.897 | D11: 58.56 | E11: 85.563 | F11: 176.181 | G11: 856.292 | H11: 1813.639 | I11: 2341.291 | J11: 4805.226 | K11: 7193.242 | L11: 21464.867 | M11: 31027.892 | N11: 56709.997
B12: 2028 | C12: 18.386 | D12: 59.628 | E12: 86.869 | F12: 179.691 | G12: 883.521 | H12: 1860.576 | I12: 2396.731 | J12: 4933.634 | K12: 7395.215 | L12: 21901.948 | M12: 31584.618 | N12: 57917.715
B13: 2029 | C13: 18.874 | D13: 60.696 | E13: 88.175 | F13: 183.201 | G13: 910.75 | H13: 1907.513 | I13: 2452.171 | J13: 5062.042 | K13: 7597.189 | L13: 22339.029 | M13: 32141.345 | N13: 59125.432
B14: 2030 | C14: 19.363 | D14: 61.764 | E14: 89.481 | F14: 186.712 | G14: 937.979 | H14: 1954.45 | I14: 2507.612 | J14: 5190.45 | K14: 7799.163 | L14: 22776.11 | M14: 32698.071 | N14: 60333.15
B15: 2031 | C15: 19.947 | D15: 62.908 | E15: 90.844 | F15: 190.535 | G15: 972.355 | H15: 2009.824 | I15: 2571.507 | J15: 5344.225 | K15: 8046.879 | L15: 23268.02 | M15: 33309.463 | N15: 61692.265
... B34: 2050 | C34: 31.66 | D34: 84.662 | E34: 116.471 | F34: 259.945 | G34: 1656.755 | H34: 3067.314 | I34: 3776.432 | J34: 8175.252 | K34: 13178.549 | L34: 32989.101 | M34: 45253.842 | N34: 88166.337

Sheet DESNZ elec carbon intensity
A1: Source: https://assets.publishing.service.gov.uk/media/6567994fcc1ec5000d8eef17/data-tables-1-19.xlsx
B4: Table 1: Electricity emissions factors to 2100, kgCO2e/kWh
B5: Consumption and generation-based emissions factors.
B7: Analysts should use consumption-based emissions factors for measuring GHG emissions per unit of final energy demand. These emissions factors include transmission and distribution losses, including significant losses due to power station inefficiency. Generation-based emissions factors measure GHG emissions per unit of electricity generated.
B9: Long-run marginal emissions factors should be used for measuring small changes in consumption or generation. Grid average emissions factors are used for footprinting.
C11: Long-run marginal | G11: Grid average
C12: Consumption-based | F12: Generation-based | G12: Consumption-based | J12: Generation-based
B13: Year | C13: Domestic | D13: Commercial/ Public sector | E13: Industrial | G13: Domestic | H13: Commercial/ Public sector | I13: Industrial
B14: 2010 | C14: 0.389 | D14: 0.382 | E14: 0.375 | F14: 0.357 | G14: 0.499 | H14: 0.49 | I14: 0.48 | J14: 0.457
B15: 2011 | C15: 0.384 | D15: 0.377 | E15: 0.37 | F15: 0.351 | G15: 0.479 | H15: 0.471 | I15: 0.462 | J15: 0.438
B16: 2012 | C16: 0.377 | D16: 0.37 | E16: 0.364 | F16: 0.344 | G16: 0.53 | H16: 0.52 | I16: 0.51 | J16: 0.483
B17: 2013 | C17: 0.368 | D17: 0.362 | E17: 0.355 | F17: 0.337 | G17: 0.493 | H17: 0.484 | I17: 0.475 | J17: 0.45
B18: 2014 | C18: 0.362 | D18: 0.355 | E18: 0.348 | F18: 0.329 | G18: 0.443 | H18: 0.434 | I18: 0.426 | J18: 0.403
B19: 2015 | C19: 0.351 | D19: 0.345 | E19: 0.338 | F19: 0.32 | G19: 0.37 | H19: 0.364 | I19: 0.357 | J19: 0.338
B20: 2016 | C20: 0.34 | D20: 0.334 | E20: 0.328 | F20: 0.311 | G20: 0.296 | H20: 0.291 | I20: 0.285 | J20: 0.271
B21: 2017 | C21: 0.33 | D21: 0.324 | E21: 0.318 | F21: 0.302 | G21: 0.265 | H21: 0.26 | I21: 0.255 | J21: 0.242
B22: 2018 | C22: 0.319 | D22: 0.313 | E22: 0.307 | F22: 0.291 | G22: 0.246 | H22: 0.241 | I22: 0.237 | J22: 0.224
B23: 2019 | C23: 0.307 | D23: 0.301 | E23: 0.295 | F23: 0.28 | G23: 0.222 | H23: 0.218 | I23: 0.214 | J23: 0.203
B24: 2020 | C24: 0.293 | D24: 0.288 | E24: 0.283 | F24: 0.268 | G24: 0.197 | H24: 0.194 | I24: 0.19 | J24: 0.18
B25: 2021 | C25: 0.279 | D25: 0.274 | E25: 0.269 | F25: 0.255 | G25: 0.217 | H25: 0.213 | I25: 0.209 | J25: 0.198
... B104: 2100 | C104: 0.003 | D104: 0.002 | E104: 0.002 | F104: 0.002 | G104: 0.003 | H104: 0.002 | I104: 0.002 | J104: 0.002
B106: Note: GHGs include CO2, CH4 and N2O.
B108: Source: DESNZmodelling
B110: Further guidance on the use of marginal and average emissions factors are available from the appraisal guidance (Chapter 3) and the background documentation (Chapter 2) which can be downloaded from the Green Gook supplementary guidance section of GOV.UK webpage:
B111: https://www.gov.uk/government/publications/valuation-of-energy-use-and-greenhouse-gas-emissions-for-appraisal

Sheet Air quality
A1: Source: https://assets.publishing.service.gov.uk/media/6567994fcc1ec5000d8eef17/data-tables-1-19.xlsx
B4: Table 15: Air quality activity costs from primary fuel use, 2022 p/kWh
B6: These are new air quality values based on the 2019 NAEI data. For use in appraisals these values should be discounted using the HMT Green Book health discount rate of 1.5%, to be consistent with interdepartmental guidance. The use of the lower health discount rate, compared to the standard 3.5% discount rate, is to reflect increases in willingness to pay for avoided health outcomes over time.
B8: The updated activity costs take into account an improved understanding of health impacts, based on the latest advice from UK Health Security Agency (UKHSA) and the Committee on the Medical Effects of Air Pollution (COMEAP). For further information on the methodology, please see https://www.gov.uk/government/publications/air-quality-impact-pathway-guidance. To note, there are some categories in Table 15 which do not have any values, denoted as N/A, because the NAEI doesn’t have any emission values for those categories.
D11: 2023 | E11: 2024 | F11: 2025 | G11: 2026 | H11: 2027 | I11: 2028 | J11: 2029 | K11: 2030 | L11: 2031 | M11: 2032 | N11: 2033 | O11: 2034 | P11: 2035 | Q11: 2036 | R11: 2037 | S11: 2038 | T11: 2039 | U11: 2040 | V11: 2041 | W11: 2042 | X11: 2043 | Y11: 2044 | Z11: 2045 | AA11: 2046 | AB11: 2047 | AC11: 2048 | AD11: 2049 | AE11: 2050 | AF11: 2051 | AG11: 2052 | AH11: 2053 | AI11: 2054 | AJ11: 2055 | AK11: 2056 | AL11: 2057 | AM11: 2058 | AN11: 2059 | AO11: 2060 | AP11: 2061 | AQ11: 2062 | AR11: 2063 | AS11: 2064 | AT11: 2065 | AU11: 2066 | AV11: 2067 | AW11: 2068 | AX11: 2069 | AY11: 2070 | AZ11: 2071 | BA11: 2072 | BB11: 2073 | BC11: 2074 | BD11: 2075 | BE11: 2076 | BF11: 2077 | BG11: 2078 | BH11: 2079 | BI11: 2080 | BJ11: 2081 | BK11: 2082 | BL11: 2083 | BM11: 2084 | BN11: 2085 | BO11: 2086 | BP11: 2087 | BQ11: 2088 | BR11: 2089 | BS11: 2090 | BT11: 2091 | BU11: 2092 | BV11: 2093 | BW11: 2094 | BX11: 2095 | BY11: 2096 | BZ11: 2097 | CA11: 2098 | CB11: 2099 | CC11: 2100
B12: NATIONAL AVERAGE
B13: Electricity | C13: (p/kWh) | D13: 0.15 | E13: 0.14 | F13: 0.13 | G13: 0.12 | H13: 0.11 | I13: 0.1 | J13: 0.09 | K13: 0.07 | L13: 0.06 | M13: 0.05 | N13: 0.04 | O13: 0.03 | P13: 0.03 | Q13: 0.02 | R13: 0.02 | S13: 0.01 | T13: 0.01 | U13: 0.01 | V13: 0.01 | W13: 0.01 | X13: 0.01 | Y13: 0.01 | Z13: 0.01 | AA13: 0.01 | AB13: 0 | AC13: 0 | AD13: 0 | AE13: 0 | AF13: 0 | AG13: 0 | AH13: 0 | AI13: 0 | AJ13: 0 | AK13: 0 | AL13: 0 | AM13: 0 | AN13: 0 | AO13: 0 | AP13: 0 | AQ13: 0 | AR13: 0 | AS13: 0 | AT13: 0 | AU13: 0 | AV13: 0 | AW13: 0 | AX13: 0 | AY13: 0 | AZ13: 0 | BA13: 0 | BB13: 0 | BC13: 0 | BD13: 0 | BE13: 0 | BF13: 0 | BG13: 0 | BH13: 0 | BI13: 0 | BJ13: 0 | BK13: 0 | BL13: 0 | BM13: 0 | BN13: 0 | BO13: 0 | BP13: 0 | BQ13: 0 | BR13: 0 | BS13: 0 | BT13: 0 | BU13: 0 | BV13: 0 | BW13: 0 | BX13: 0 | BY13: 0 | BZ13: 0 | CA13: 0 | CB13: 0 | CC13: 0
B14: Gas | C14: (p/kWh) | D14: 0.16 | E14: 0.16 | F14: 0.16 | G14: 0.16 | H14: 0.16 | I14: 0.16 | J14: 0.16 | K14: 0.16 | L14: 0.16 | M14: 0.16 | N14: 0.16 | O14: 0.16 | P14: 0.16 | Q14: 0.16 | R14: 0.16 | S14: 0.16 | T14: 0.16 | U14: 0.16 | V14: 0.16 | W14: 0.16 | X14: 0.16 | Y14: 0.16 | Z14: 0.16 | AA14: 0.16 | AB14: 0.16 | AC14: 0.16 | AD14: 0.16 | AE14: 0.16 | AF14: 0.16 | AG14: 0.16 | AH14: 0.16 | AI14: 0.16 | AJ14: 0.16 | AK14: 0.16 | AL14: 0.16 | AM14: 0.16 | AN14: 0.16 | AO14: 0.16 | AP14: 0.16 | AQ14: 0.16 | AR14: 0.16 | AS14: 0.16 | AT14: 0.16 | AU14: 0.16 | AV14: 0.16 | AW14: 0.16 | AX14: 0.16 | AY14: 0.16 | AZ14: 0.16 | BA14: 0.16 | BB14: 0.16 | BC14: 0.16 | BD14: 0.16 | BE14: 0.16 | BF14: 0.16 | BG14: 0.16 | BH14: 0.16 | BI14: 0.16 | BJ14: 0.16 | BK14: 0.16 | BL14: 0.16 | BM14: 0.16 | BN14: 0.16 | BO14: 0.16 | BP14: 0.16 | BQ14: 0.16 | BR14: 0.16 | BS14: 0.16 | BT14: 0.16 | BU14: 0.16 | BV14: 0.16 | BW14: 0.16 | BX14: 0.16 | BY14: 0.16 | BZ14: 0.16 | CA14: 0.16 | CB14: 0.16 | CC14: 0.16
B15: Coal | C15: (p/kWh) | D15: 3.74 | E15: 3.74 | F15: 3.74 | G15: 3.74 | H15: 3.74 | I15: 3.74 | J15: 3.74 | K15: 3.74 | L15: 3.74 | M15: 3.74 | N15: 3.74 | O15: 3.74 | P15: 3.74 | Q15: 3.74 | R15: 3.74 | S15: 3.74 | T15: 3.74 | U15: 3.74 | V15: 3.74 | W15: 3.74 | X15: 3.74 | Y15: 3.74 | Z15: 3.74 | AA15: 3.74 | AB15: 3.74 | AC15: 3.74 | AD15: 3.74 | AE15: 3.74 | AF15: 3.74 | AG15: 3.74 | AH15: 3.74 | AI15: 3.74 | AJ15: 3.74 | AK15: 3.74 | AL15: 3.74 | AM15: 3.74 | AN15: 3.74 | AO15: 3.74 | AP15: 3.74 | AQ15: 3.74 | AR15: 3.74 | AS15: 3.74 | AT15: 3.74 | AU15: 3.74 | AV15: 3.74 | AW15: 3.74 | AX15: 3.74 | AY15: 3.74 | AZ15: 3.74 | BA15: 3.74 | BB15: 3.74 | BC15: 3.74 | BD15: 3.74 | BE15: 3.74 | BF15: 3.74 | BG15: 3.74 | BH15: 3.74 | BI15: 3.74 | BJ15: 3.74 | BK15: 3.74 | BL15: 3.74 | BM15: 3.74 | BN15: 3.74 | BO15: 3.74 | BP15: 3.74 | BQ15: 3.74 | BR15: 3.74 | BS15: 3.74 | BT15: 3.74 | BU15: 3.74 | BV15: 3.74 | BW15: 3.74 | BX15: 3.74 | BY15: 3.74 | BZ15: 3.74 | CA15: 3.74 | CB15: 3.74 | CC15: 3.74
B16: Burning oil | C16: (p/kWh) | D16: 2.28 | E16: 2.28 | F16: 2.28 | G16: 2.28 | H16: 2.28 | I16: 2.28 | J16: 2.28 | K16: 2.28 | L16: 2.28 | M16: 2.28 | N16: 2.28 | O16: 2.28 | P16: 2.28 | Q16: 2.28 | R16: 2.28 | S16: 2.28 | T16: 2.28 | U16: 2.28 | V16: 2.28 | W16: 2.28 | X16: 2.28 | Y16: 2.28 | Z16: 2.28 | AA16: 2.28 | AB16: 2.28 | AC16: 2.28 | AD16: 2.28 | AE16: 2.28 | AF16: 2.28 | AG16: 2.28 | AH16: 2.28 | AI16: 2.28 | AJ16: 2.28 | AK16: 2.28 | AL16: 2.28 | AM16: 2.28 | AN16: 2.28 | AO16: 2.28 | AP16: 2.28 | AQ16: 2.28 | AR16: 2.28 | AS16: 2.28 | AT16: 2.28 | AU16: 2.28 | AV16: 2.28 | AW16: 2.28 | AX16: 2.28 | AY16: 2.28 | AZ16: 2.28 | BA16: 2.28 | BB16: 2.28 | BC16: 2.28 | BD16: 2.28 | BE16: 2.28 | BF16: 2.28 | BG16: 2.28 | BH16: 2.28 | BI16: 2.28 | BJ16: 2.28 | BK16: 2.28 | BL16: 2.28 | BM16: 2.28 | BN16: 2.28 | BO16: 2.28 | BP16: 2.28 | BQ16: 2.28 | BR16: 2.28 | BS16: 2.28 | BT16: 2.28 | BU16: 2.28 | BV16: 2.28 | BW16: 2.28 | BX16: 2.28 | BY16: 2.28 | BZ16: 2.28 | CA16: 2.28 | CB16: 2.28 | CC16: 2.28
B17: Biomass | C17: (p/kWh) | D17: 4.7 | E17: 4.7 | F17: 4.7 | G17: 4.7 | H17: 4.7 | I17: 4.7 | J17: 4.7 | K17: 4.7 | L17: 4.7 | M17: 4.7 | N17: 4.7 | O17: 4.7 | P17: 4.7 | Q17: 4.7 | R17: 4.7 | S17: 4.7 | T17: 4.7 | U17: 4.7 | V17: 4.7 | W17: 4.7 | X17: 4.7 | Y17: 4.7 | Z17: 4.7 | AA17: 4.7 | AB17: 4.7 | AC17: 4.7 | AD17: 4.7 | AE17: 4.7 | AF17: 4.7 | AG17: 4.7 | AH17: 4.7 | AI17: 4.7 | AJ17: 4.7 | AK17: 4.7 | AL17: 4.7 | AM17: 4.7 | AN17: 4.7 | AO17: 4.7 | AP17: 4.7 | AQ17: 4.7 | AR17: 4.7 | AS17: 4.7 | AT17: 4.7 | AU17: 4.7 | AV17: 4.7 | AW17: 4.7 | AX17: 4.7 | AY17: 4.7 | AZ17: 4.7 | BA17: 4.7 | BB17: 4.7 | BC17: 4.7 | BD17: 4.7 | BE17: 4.7 | BF17: 4.7 | BG17: 4.7 | BH17: 4.7 | BI17: 4.7 | BJ17: 4.7 | BK17: 4.7 | BL17: 4.7 | BM17: 4.7 | BN17: 4.7 | BO17: 4.7 | BP17: 4.7 | BQ17: 4.7 | BR17: 4.7 | BS17: 4.7 | BT17: 4.7 | BU17: 4.7 | BV17: 4.7 | BW17: 4.7 | BX17: 4.7 | BY17: 4.7 | BZ17: 4.7 | CA17: 4.7 | CB17: 4.7 | CC17: 4.7
B18: LPG | C18: (p/kWh) | D18: 0.22 | E18: 0.22 | F18: 0.22 | G18: 0.22 | H18: 0.22 | I18: 0.22 | J18: 0.22 | K18: 0.22 | L18: 0.22 | M18: 0.22 | N18: 0.22 | O18: 0.22 | P18: 0.22 | Q18: 0.22 | R18: 0.22 | S18: 0.22 | T18: 0.22 | U18: 0.22 | V18: 0.22 | W18: 0.22 | X18: 0.22 | Y18: 0.22 | Z18: 0.22 | AA18: 0.22 | AB18: 0.22 | AC18: 0.22 | AD18: 0.22 | AE18: 0.22 | AF18: 0.22 | AG18: 0.22 | AH18: 0.22 | AI18: 0.22 | AJ18: 0.22 | AK18: 0.22 | AL18: 0.22 | AM18: 0.22 | AN18: 0.22 | AO18: 0.22 | AP18: 0.22 | AQ18: 0.22 | AR18: 0.22 | AS18: 0.22 | AT18: 0.22 | AU18: 0.22 | AV18: 0.22 | AW18: 0.22 | AX18: 0.22 | AY18: 0.22 | AZ18: 0.22 | BA18: 0.22 | BB18: 0.22 | BC18: 0.22 | BD18: 0.22 | BE18: 0.22 | BF18: 0.22 | BG18: 0.22 | BH18: 0.22 | BI18: 0.22 | BJ18: 0.22 | BK18: 0.22 | BL18: 0.22 | BM18: 0.22 | BN18: 0.22 | BO18: 0.22 | BP18: 0.22 | BQ18: 0.22 | BR18: 0.22 | BS18: 0.22 | BT18: 0.22 | BU18: 0.22 | BV18: 0.22 | BW18: 0.22 | BX18: 0.22 | BY18: 0.22 | BZ18: 0.22 | CA18: 0.22 | CB18: 0.22 | CC18: 0.22
B19: Peat | C19: (p/kWh) | D19: 21.43 | E19: 21.43 | F19: 21.43 | G19: 21.43 | H19: 21.43 | I19: 21.43 | J19: 21.43 | K19: 21.43 | L19: 21.43 | M19: 21.43 | N19: 21.43 | O19: 21.43 | P19: 21.43 | Q19: 21.43 | R19: 21.43 | S19: 21.43 | T19: 21.43 | U19: 21.43 | V19: 21.43 | W19: 21.43 | X19: 21.43 | Y19: 21.43 | Z19: 21.43 | AA19: 21.43 | AB19: 21.43 | AC19: 21.43 | AD19: 21.43 | AE19: 21.43 | AF19: 21.43 | AG19: 21.43 | AH19: 21.43 | AI19: 21.43 | AJ19: 21.43 | AK19: 21.43 | AL19: 21.43 | AM19: 21.43 | AN19: 21.43 | AO19: 21.43 | AP19: 21.43 | AQ19: 21.43 | AR19: 21.43 | AS19: 21.43 | AT19: 21.43 | AU19: 21.43 | AV19: 21.43 | AW19: 21.43 | AX19: 21.43 | AY19: 21.43 | AZ19: 21.43 | BA19: 21.43 | BB19: 21.43 | BC19: 21.43 | BD19: 21.43 | BE19: 21.43 | BF19: 21.43 | BG19: 21.43 | BH19: 21.43 | BI19: 21.43 | BJ19: 21.43 | BK19: 21.43 | BL19: 21.43 | BM19: 21.43 | BN19: 21.43 | BO19: 21.43 | BP19: 21.43 | BQ19: 21.43 | BR19: 21.43 | BS19: 21.43 | BT19: 21.43 | BU19: 21.43 | BV19: 21.43 | BW19: 21.43 | BX19: 21.43 | BY19: 21.43 | BZ19: 21.43 | CA19: 21.43 | CB19: 21.43 | CC19: 21.43
B20: Petroleum coke | C20: (p/kWh) | D20: 7.36 | E20: 7.36 | F20: 7.36 | G20: 7.36 | H20: 7.36 | I20: 7.36 | J20: 7.36 | K20: 7.36 | L20: 7.36 | M20: 7.36 | N20: 7.36 | O20: 7.36 | P20: 7.36 | Q20: 7.36 | R20: 7.36 | S20: 7.36 | T20: 7.36 | U20: 7.36 | V20: 7.36 | W20: 7.36 | X20: 7.36 | Y20: 7.36 | Z20: 7.36 | AA20: 7.36 | AB20: 7.36 | AC20: 7.36 | AD20: 7.36 | AE20: 7.36 | AF20: 7.36 | AG20: 7.36 | AH20: 7.36 | AI20: 7.36 | AJ20: 7.36 | AK20: 7.36 | AL20: 7.36 | AM20: 7.36 | AN20: 7.36 | AO20: 7.36 | AP20: 7.36 | AQ20: 7.36 | AR20: 7.36 | AS20: 7.36 | AT20: 7.36 | AU20: 7.36 | AV20: 7.36 | AW20: 7.36 | AX20: 7.36 | AY20: 7.36 | AZ20: 7.36 | BA20: 7.36 | BB20: 7.36 | BC20: 7.36 | BD20: 7.36 | BE20: 7.36 | BF20: 7.36 | BG20: 7.36 | BH20: 7.36 | BI20: 7.36 | BJ20: 7.36 | BK20: 7.36 | BL20: 7.36 | BM20: 7.36 | BN20: 7.36 | BO20: 7.36 | BP20: 7.36 | BQ20: 7.36 | BR20: 7.36 | BS20: 7.36 | BT20: 7.36 | BU20: 7.36 | BV20: 7.36 | BW20: 7.36 | BX20: 7.36 | BY20: 7.36 | BZ20: 7.36 | CA20: 7.36 | CB20: 7.36 | CC20: 7.36
B22: DOMESTIC: Inner conurbation
B23: Gas | C23: (p/kWh) | D23: 0.23 | E23: 0.23 | F23: 0.23 | G23: 0.23 | H23: 0.23 | I23: 0.23 | J23: 0.23 | K23: 0.23 | L23: 0.23 | M23: 0.23 | N23: 0.23 | O23: 0.23 | P23: 0.23 | Q23: 0.23 | R23: 0.23 | S23: 0.23 | T23: 0.23 | U23: 0.23 | V23: 0.23 | W23: 0.23 | X23: 0.23 | Y23: 0.23 | Z23: 0.23 | AA23: 0.23 | AB23: 0.23 | AC23: 0.23 | AD23: 0.23 | AE23: 0.23 | AF23: 0.23 | AG23: 0.23 | AH23: 0.23 | AI23: 0.23 | AJ23: 0.23 | AK23: 0.23 | AL23: 0.23 | AM23: 0.23 | AN23: 0.23 | AO23: 0.23 | AP23: 0.23 | AQ23: 0.23 | AR23: 0.23 | AS23: 0.23 | AT23: 0.23 | AU23: 0.23 | AV23: 0.23 | AW23: 0.23 | AX23: 0.23 | AY23: 0.23 | AZ23: 0.23 | BA23: 0.23 | BB23: 0.23 | BC23: 0.23 | BD23: 0.23 | BE23: 0.23 | BF23: 0.23 | BG23: 0.23 | BH23: 0.23 | BI23: 0.23 | BJ23: 0.23 | BK23: 0.23 | BL23: 0.23 | BM23: 0.23 | BN23: 0.23 | BO23: 0.23 | BP23: 0.23 | BQ23: 0.23 | BR23: 0.23 | BS23: 0.23 | BT23: 0.23 | BU23: 0.23 | BV23: 0.23 | BW23: 0.23 | BX23: 0.23 | BY23: 0.23 | BZ23: 0.23 | CA23: 0.23 | CB23: 0.23 | CC23: 0.23
B24: Coal | C24: (p/kWh) | D24: 14.56 | E24: 14.56 | F24: 14.56 | G24: 14.56 | H24: 14.56 | I24: 14.56 | J24: 14.56 | K24: 14.56 | L24: 14.56 | M24: 14.56 | N24: 14.56 | O24: 14.56 | P24: 14.56 | Q24: 14.56 | R24: 14.56 | S24: 14.56 | T24: 14.56 | U24: 14.56 | V24: 14.56 | W24: 14.56 | X24: 14.56 | Y24: 14.56 | Z24: 14.56 | AA24: 14.56 | AB24: 14.56 | AC24: 14.56 | AD24: 14.56 | AE24: 14.56 | AF24: 14.56 | AG24: 14.56 | AH24: 14.56 | AI24: 14.56 | AJ24: 14.56 | AK24: 14.56 | AL24: 14.56 | AM24: 14.56 | AN24: 14.56 | AO24: 14.56 | AP24: 14.56 | AQ24: 14.56 | AR24: 14.56 | AS24: 14.56 | AT24: 14.56 | AU24: 14.56 | AV24: 14.56 | AW24: 14.56 | AX24: 14.56 | AY24: 14.56 | AZ24: 14.56 | BA24: 14.56 | BB24: 14.56 | BC24: 14.56 | BD24: 14.56 | BE24: 14.56 | BF24: 14.56 | BG24: 14.56 | BH24: 14.56 | BI24: 14.56 | BJ24: 14.56 | BK24: 14.56 | BL24: 14.56 | BM24: 14.56 | BN24: 14.56 | BO24: 14.56 | BP24: 14.56 | BQ24: 14.56 | BR24: 14.56 | BS24: 14.56 | BT24: 14.56 | BU24: 14.56 | BV24: 14.56 | BW24: 14.56 | BX24: 14.56 | BY24: 14.56 | BZ24: 14.56 | CA24: 14.56 | CB24: 14.56 | CC24: 14.56
B25: Burning oil | C25: (p/kWh) | D25: 0.63 | E25: 0.63 | F25: 0.63 | G25: 0.63 | H25: 0.63 | I25: 0.63 | J25: 0.63 | K25: 0.63 | L25: 0.63 | M25: 0.63 | N25: 0.63 | O25: 0.63 | P25: 0.63 | Q25: 0.63 | R25: 0.63 | S25: 0.63 | T25: 0.63 | U25: 0.63 | V25: 0.63 | W25: 0.63 | X25: 0.63 | Y25: 0.63 | Z25: 0.63 | AA25: 0.63 | AB25: 0.63 | AC25: 0.63 | AD25: 0.63 | AE25: 0.63 | AF25: 0.63 | AG25: 0.63 | AH25: 0.63 | AI25: 0.63 | AJ25: 0.63 | AK25: 0.63 | AL25: 0.63 | AM25: 0.63 | AN25: 0.63 | AO25: 0.63 | AP25: 0.63 | AQ25: 0.63 | AR25: 0.63 | AS25: 0.63 | AT25: 0.63 | AU25: 0.63 | AV25: 0.63 | AW25: 0.63 | AX25: 0.63 | AY25: 0.63 | AZ25: 0.63 | BA25: 0.63 | BB25: 0.63 | BC25: 0.63 | BD25: 0.63 | BE25: 0.63 | BF25: 0.63 | BG25: 0.63 | BH25: 0.63 | BI25: 0.63 | BJ25: 0.63 | BK25: 0.63 | BL25: 0.63 | BM25: 0.63 | BN25: 0.63 | BO25: 0.63 | BP25: 0.63 | BQ25: 0.63 | BR25: 0.63 | BS25: 0.63 | BT25: 0.63 | BU25: 0.63 | BV25: 0.63 | BW25: 0.63 | BX25: 0.63 | BY25: 0.63 | BZ25: 0.63 | CA25: 0.63 | CB25: 0.63 | CC25: 0.63
B26: Biomass | C26: (p/kWh) | D26: 29.2 | E26: 29.2 | F26: 29.2 | G26: 29.2 | H26: 29.2 | I26: 29.2 | J26: 29.2 | K26: 29.2 | L26: 29.2 | M26: 29.2 | N26: 29.2 | O26: 29.2 | P26: 29.2 | Q26: 29.2 | R26: 29.2 | S26: 29.2 | T26: 29.2 | U26: 29.2 | V26: 29.2 | W26: 29.2 | X26: 29.2 | Y26: 29.2 | Z26: 29.2 | AA26: 29.2 | AB26: 29.2 | AC26: 29.2 | AD26: 29.2 | AE26: 29.2 | AF26: 29.2 | AG26: 29.2 | AH26: 29.2 | AI26: 29.2 | AJ26: 29.2 | AK26: 29.2 | AL26: 29.2 | AM26: 29.2 | AN26: 29.2 | AO26: 29.2 | AP26: 29.2 | AQ26: 29.2 | AR26: 29.2 | AS26: 29.2 | AT26: 29.2 | AU26: 29.2 | AV26: 29.2 | AW26: 29.2 | AX26: 29.2 | AY26: 29.2 | AZ26: 29.2 | BA26: 29.2 | BB26: 29.2 | BC26: 29.2 | BD26: 29.2 | BE26: 29.2 | BF26: 29.2 | BG26: 29.2 | BH26: 29.2 | BI26: 29.2 | BJ26: 29.2 | BK26: 29.2 | BL26: 29.2 | BM26: 29.2 | BN26: 29.2 | BO26: 29.2 | BP26: 29.2 | BQ26: 29.2 | BR26: 29.2 | BS26: 29.2 | BT26: 29.2 | BU26: 29.2 | BV26: 29.2 | BW26: 29.2 | BX26: 29.2 | BY26: 29.2 | BZ26: 29.2 | CA26: 29.2 | CB26: 29.2 | CC26: 29.2
B27: LPG | C27: (p/kWh) | D27: N/A | E27: N/A | F27: N/A | G27: N/A | H27: N/A | I27: N/A | J27: N/A | K27: N/A | L27: N/A | M27: N/A | N27: N/A | O27: N/A | P27: N/A | Q27: N/A | R27: N/A | S27: N/A | T27: N/A | U27: N/A | V27: N/A | W27: N/A | X27: N/A | Y27: N/A | Z27: N/A | AA27: N/A | AB27: N/A | AC27: N/A | AD27: N/A | AE27: N/A | AF27: N/A | AG27: N/A | AH27: N/A | AI27: N/A | AJ27: N/A | AK27: N/A | AL27: N/A | AM27: N/A | AN27: N/A | AO27: N/A | AP27: N/A | AQ27: N/A | AR27: N/A | AS27: N/A | AT27: N/A | AU27: N/A | AV27: N/A | AW27: N/A | AX27: N/A | AY27: N/A | AZ27: N/A | BA27: N/A | BB27: N/A | BC27: N/A | BD27: N/A | BE27: N/A | BF27: N/A | BG27: N/A | BH27: N/A | BI27: N/A | BJ27: N/A | BK27: N/A | BL27: N/A | BM27: N/A | BN27: N/A | BO27: N/A | BP27: N/A | BQ27: N/A | BR27: N/A | BS27: N/A | BT27: N/A | BU27: N/A | BV27: N/A | BW27: N/A | BX27: N/A | BY27: N/A | BZ27: N/A | CA27: N/A | CB27: N/A | CC27: N/A
B28: Peat | C28: (p/kWh) | D28: N/A | E28: N/A | F28: N/A | G28: N/A | H28: N/A | I28: N/A | J28: N/A | K28: N/A | L28: N/A | M28: N/A | N28: N/A | O28: N/A | P28: N/A | Q28: N/A | R28: N/A | S28: N/A | T28: N/A | U28: N/A | V28: N/A | W28: N/A | X28: N/A | Y28: N/A | Z28: N/A | AA28: N/A | AB28: N/A | AC28: N/A | AD28: N/A | AE28: N/A | AF28: N/A | AG28: N/A | AH28: N/A | AI28: N/A | AJ28: N/A | AK28: N/A | AL28: N/A | AM28: N/A | AN28: N/A | AO28: N/A | AP28: N/A | AQ28: N/A | AR28: N/A | AS28: N/A | AT28: N/A | AU28: N/A | AV28: N/A | AW28: N/A | AX28: N/A | AY28: N/A | AZ28: N/A | BA28: N/A | BB28: N/A | BC28: N/A | BD28: N/A | BE28: N/A | BF28: N/A | BG28: N/A | BH28: N/A | BI28: N/A | BJ28: N/A | BK28: N/A | BL28: N/A | BM28: N/A | BN28: N/A | BO28: N/A | BP28: N/A | BQ28: N/A | BR28: N/A | BS28: N/A | BT28: N/A | BU28: N/A | BV28: N/A | BW28: N/A | BX28: N/A | BY28: N/A | BZ28: N/A | CA28: N/A | CB28: N/A | CC28: N/A
B29: Petroleum coke | C29: (p/kWh) | D29: 29.57 | E29: 29.57 | F29: 29.57 | G29: 29.57 | H29: 29.57 | I29: 29.57 | J29: 29.57 | K29: 29.57 | L29: 29.57 | M29: 29.57 | N29: 29.57 | O29: 29.57 | P29: 29.57 | Q29: 29.57 | R29: 29.57 | S29: 29.57 | T29: 29.57 | U29: 29.57 | V29: 29.57 | W29: 29.57 | X29: 29.57 | Y29: 29.57 | Z29: 29.57 | AA29: 29.57 | AB29: 29.57 | AC29: 29.57 | AD29: 29.57 | AE29: 29.57 | AF29: 29.57 | AG29: 29.57 | AH29: 29.57 | AI29: 29.57 | AJ29: 29.57 | AK29: 29.57 | AL29: 29.57 | AM29: 29.57 | AN29: 29.57 | AO29: 29.57 | AP29: 29.57 | AQ29: 29.57 | AR29: 29.57 | AS29: 29.57 | AT29: 29.57 | AU29: 29.57 | AV29: 29.57 | AW29: 29.57 | AX29: 29.57 | AY29: 29.57 | AZ29: 29.57 | BA29: 29.57 | BB29: 29.57 | BC29: 29.57 | BD29: 29.57 | BE29: 29.57 | BF29: 29.57 | BG29: 29.57 | BH29: 29.57 | BI29: 29.57 | BJ29: 29.57 | BK29: 29.57 | BL29: 29.57 | BM29: 29.57 | BN29: 29.57 | BO29: 29.57 | BP29: 29.57 | BQ29: 29.57 | BR29: 29.57 | BS29: 29.57 | BT29: 29.57 | BU29: 29.57 | BV29: 29.57 | BW29: 29.57 | BX29: 29.57 | BY29: 29.57 | BZ29: 29.57 | CA29: 29.57 | CB29: 29.57 | CC29: 29.57
B31: DOMESTIC: Urban big
B32: Gas | C32: (p/kWh) | D32: 0.14 | E32: 0.14 | F32: 0.14 | G32: 0.14 | H32: 0.14 | I32: 0.14 | J32: 0.14 | K32: 0.14 | L32: 0.14 | M32: 0.14 | N32: 0.14 | O32: 0.14 | P32: 0.14 | Q32: 0.14 | R32: 0.14 | S32: 0.14 | T32: 0.14 | U32: 0.14 | V32: 0.14 | W32: 0.14 | X32: 0.14 | Y32: 0.14 | Z32: 0.14 | AA32: 0.14 | AB32: 0.14 | AC32: 0.14 | AD32: 0.14 | AE32: 0.14 | AF32: 0.14 | AG32: 0.14 | AH32: 0.14 | AI32: 0.14 | AJ32: 0.14 | AK32: 0.14 | AL32: 0.14 | AM32: 0.14 | AN32: 0.14 | AO32: 0.14 | AP32: 0.14 | AQ32: 0.14 | AR32: 0.14 | AS32: 0.14 | AT32: 0.14 | AU32: 0.14 | AV32: 0.14 | AW32: 0.14 | AX32: 0.14 | AY32: 0.14 | AZ32: 0.14 | BA32: 0.14 | BB32: 0.14 | BC32: 0.14 | BD32: 0.14 | BE32: 0.14 | BF32: 0.14 | BG32: 0.14 | BH32: 0.14 | BI32: 0.14 | BJ32: 0.14 | BK32: 0.14 | BL32: 0.14 | BM32: 0.14 | BN32: 0.14 | BO32: 0.14 | BP32: 0.14 | BQ32: 0.14 | BR32: 0.14 | BS32: 0.14 | BT32: 0.14 | BU32: 0.14 | BV32: 0.14 | BW32: 0.14 | BX32: 0.14 | BY32: 0.14 | BZ32: 0.14 | CA32: 0.14 | CB32: 0.14 | CC32: 0.14
B33: Coal | C33: (p/kWh) | D33: 9.62 | E33: 9.62 | F33: 9.62 | G33: 9.62 | H33: 9.62 | I33: 9.62 | J33: 9.62 | K33: 9.62 | L33: 9.62 | M33: 9.62 | N33: 9.62 | O33: 9.62 | P33: 9.62 | Q33: 9.62 | R33: 9.62 | S33: 9.62 | T33: 9.62 | U33: 9.62 | V33: 9.62 | W33: 9.62 | X33: 9.62 | Y33: 9.62 | Z33: 9.62 | AA33: 9.62 | AB33: 9.62 | AC33: 9.62 | AD33: 9.62 | AE33: 9.62 | AF33: 9.62 | AG33: 9.62 | AH33: 9.62 | AI33: 9.62 | AJ33: 9.62 | AK33: 9.62 | AL33: 9.62 | AM33: 9.62 | AN33: 9.62 | AO33: 9.62 | AP33: 9.62 | AQ33: 9.62 | AR33: 9.62 | AS33: 9.62 | AT33: 9.62 | AU33: 9.62 | AV33: 9.62 | AW33: 9.62 | AX33: 9.62 | AY33: 9.62 | AZ33: 9.62 | BA33: 9.62 | BB33: 9.62 | BC33: 9.62 | BD33: 9.62 | BE33: 9.62 | BF33: 9.62 | BG33: 9.62 | BH33: 9.62 | BI33: 9.62 | BJ33: 9.62 | BK33: 9.62 | BL33: 9.62 | BM33: 9.62 | BN33: 9.62 | BO33: 9.62 | BP33: 9.62 | BQ33: 9.62 | BR33: 9.62 | BS33: 9.62 | BT33: 9.62 | BU33: 9.62 | BV33: 9.62 | BW33: 9.62 | BX33: 9.62 | BY33: 9.62 | BZ33: 9.62 | CA33: 9.62 | CB33: 9.62 | CC33: 9.62
B34: Burning oil | C34: (p/kWh) | D34: 0.3 | E34: 0.3 | F34: 0.3 | G34: 0.3 | H34: 0.3 | I34: 0.3 | J34: 0.3 | K34: 0.3 | L34: 0.3 | M34: 0.3 | N34: 0.3 | O34: 0.3 | P34: 0.3 | Q34: 0.3 | R34: 0.3 | S34: 0.3 | T34: 0.3 | U34: 0.3 | V34: 0.3 | W34: 0.3 | X34: 0.3 | Y34: 0.3 | Z34: 0.3 | AA34: 0.3 | AB34: 0.3 | AC34: 0.3 | AD34: 0.3 | AE34: 0.3 | AF34: 0.3 | AG34: 0.3 | AH34: 0.3 | AI34: 0.3 | AJ34: 0.3 | AK34: 0.3 | AL34: 0.3 | AM34: 0.3 | AN34: 0.3 | AO34: 0.3 | AP34: 0.3 | AQ34: 0.3 | AR34: 0.3 | AS34: 0.3 | AT34: 0.3 | AU34: 0.3 | AV34: 0.3 | AW34: 0.3 | AX34: 0.3 | AY34: 0.3 | AZ34: 0.3 | BA34: 0.3 | BB34: 0.3 | BC34: 0.3 | BD34: 0.3 | BE34: 0.3 | BF34: 0.3 | BG34: 0.3 | BH34: 0.3 | BI34: 0.3 | BJ34: 0.3 | BK34: 0.3 | BL34: 0.3 | BM34: 0.3 | BN34: 0.3 | BO34: 0.3 | BP34: 0.3 | BQ34: 0.3 | BR34: 0.3 | BS34: 0.3 | BT34: 0.3 | BU34: 0.3 | BV34: 0.3 | BW34: 0.3 | BX34: 0.3 | BY34: 0.3 | BZ34: 0.3 | CA34: 0.3 | CB34: 0.3 | CC34: 0.3
B35: Biomass | C35: (p/kWh) | D35: 16.77 | E35: 16.77 | F35: 16.77 | G35: 16.77 | H35: 16.77 | I35: 16.77 | J35: 16.77 | K35: 16.77 | L35: 16.77 | M35: 16.77 | N35: 16.77 | O35: 16.77 | P35: 16.77 | Q35: 16.77 | R35: 16.77 | S35: 16.77 | T35: 16.77 | U35: 16.77 | V35: 16.77 | W35: 16.77 | X35: 16.77 | Y35: 16.77 | Z35: 16.77 | AA35: 16.77 | AB35: 16.77 | AC35: 16.77 | AD35: 16.77 | AE35: 16.77 | AF35: 16.77 | AG35: 16.77 | AH35: 16.77 | AI35: 16.77 | AJ35: 16.77 | AK35: 16.77 | AL35: 16.77 | AM35: 16.77 | AN35: 16.77 | AO35: 16.77 | AP35: 16.77 | AQ35: 16.77 | AR35: 16.77 | AS35: 16.77 | AT35: 16.77 | AU35: 16.77 | AV35: 16.77 | AW35: 16.77 | AX35: 16.77 | AY35: 16.77 | AZ35: 16.77 | BA35: 16.77 | BB35: 16.77 | BC35: 16.77 | BD35: 16.77 | BE35: 16.77 | BF35: 16.77 | BG35: 16.77 | BH35: 16.77 | BI35: 16.77 | BJ35: 16.77 | BK35: 16.77 | BL35: 16.77 | BM35: 16.77 | BN35: 16.77 | BO35: 16.77 | BP35: 16.77 | BQ35: 16.77 | BR35: 16.77 | BS35: 16.77 | BT35: 16.77 | BU35: 16.77 | BV35: 16.77 | BW35: 16.77 | BX35: 16.77 | BY35: 16.77 | BZ35: 16.77 | CA35: 16.77 | CB35: 16.77 | CC35: 16.77
B36: LPG | C36: (p/kWh) | D36: N/A | E36: N/A | F36: N/A | G36: N/A | H36: N/A | I36: N/A | J36: N/A | K36: N/A | L36: N/A | M36: N/A | N36: N/A | O36: N/A | P36: N/A | Q36: N/A | R36: N/A | S36: N/A | T36: N/A | U36: N/A | V36: N/A | W36: N/A | X36: N/A | Y36: N/A | Z36: N/A | AA36: N/A | AB36: N/A | AC36: N/A | AD36: N/A | AE36: N/A | AF36: N/A | AG36: N/A | AH36: N/A | AI36: N/A | AJ36: N/A | AK36: N/A | AL36: N/A | AM36: N/A | AN36: N/A | AO36: N/A | AP36: N/A | AQ36: N/A | AR36: N/A | AS36: N/A | AT36: N/A | AU36: N/A | AV36: N/A | AW36: N/A | AX36: N/A | AY36: N/A | AZ36: N/A | BA36: N/A | BB36: N/A | BC36: N/A | BD36: N/A | BE36: N/A | BF36: N/A | BG36: N/A | BH36: N/A | BI36: N/A | BJ36: N/A | BK36: N/A | BL36: N/A | BM36: N/A | BN36: N/A | BO36: N/A | BP36: N/A | BQ36: N/A | BR36: N/A | BS36: N/A | BT36: N/A | BU36: N/A | BV36: N/A | BW36: N/A | BX36: N/A | BY36: N/A | BZ36: N/A | CA36: N/A | CB36: N/A | CC36: N/A
B37: Peat | C37: (p/kWh) | D37: 27.94 | E37: 27.94 | F37: 27.94 | G37: 27.94 | H37: 27.94 | I37: 27.94 | J37: 27.94 | K37: 27.94 | L37: 27.94 | M37: 27.94 | N37: 27.94 | O37: 27.94 | P37: 27.94 | Q37: 27.94 | R37: 27.94 | S37: 27.94 | T37: 27.94 | U37: 27.94 | V37: 27.94 | W37: 27.94 | X37: 27.94 | Y37: 27.94 | Z37: 27.94 | AA37: 27.94 | AB37: 27.94 | AC37: 27.94 | AD37: 27.94 | AE37: 27.94 | AF37: 27.94 | AG37: 27.94 | AH37: 27.94 | AI37: 27.94 | AJ37: 27.94 | AK37: 27.94 | AL37: 27.94 | AM37: 27.94 | AN37: 27.94 | AO37: 27.94 | AP37: 27.94 | AQ37: 27.94 | AR37: 27.94 | AS37: 27.94 | AT37: 27.94 | AU37: 27.94 | AV37: 27.94 | AW37: 27.94 | AX37: 27.94 | AY37: 27.94 | AZ37: 27.94 | BA37: 27.94 | BB37: 27.94 | BC37: 27.94 | BD37: 27.94 | BE37: 27.94 | BF37: 27.94 | BG37: 27.94 | BH37: 27.94 | BI37: 27.94 | BJ37: 27.94 | BK37: 27.94 | BL37: 27.94 | BM37: 27.94 | BN37: 27.94 | BO37: 27.94 | BP37: 27.94 | BQ37: 27.94 | BR37: 27.94 | BS37: 27.94 | BT37: 27.94 | BU37: 27.94 | BV37: 27.94 | BW37: 27.94 | BX37: 27.94 | BY37: 27.94 | BZ37: 27.94 | CA37: 27.94 | CB37: 27.94 | CC37: 27.94
B38: Petroleum coke | C38: (p/kWh) | D38: 27.65 | E38: 27.65 | F38: 27.65 | G38: 27.65 | H38: 27.65 | I38: 27.65 | J38: 27.65 | K38: 27.65 | L38: 27.65 | M38: 27.65 | N38: 27.65 | O38: 27.65 | P38: 27.65 | Q38: 27.65 | R38: 27.65 | S38: 27.65 | T38: 27.65 | U38: 27.65 | V38: 27.65 | W38: 27.65 | X38: 27.65 | Y38: 27.65 | Z38: 27.65 | AA38: 27.65 | AB38: 27.65 | AC38: 27.65 | AD38: 27.65 | AE38: 27.65 | AF38: 27.65 | AG38: 27.65 | AH38: 27.65 | AI38: 27.65 | AJ38: 27.65 | AK38: 27.65 | AL38: 27.65 | AM38: 27.65 | AN38: 27.65 | AO38: 27.65 | AP38: 27.65 | AQ38: 27.65 | AR38: 27.65 | AS38: 27.65 | AT38: 27.65 | AU38: 27.65 | AV38: 27.65 | AW38: 27.65 | AX38: 27.65 | AY38: 27.65 | AZ38: 27.65 | BA38: 27.65 | BB38: 27.65 | BC38: 27.65 | BD38: 27.65 | BE38: 27.65 | BF38: 27.65 | BG38: 27.65 | BH38: 27.65 | BI38: 27.65 | BJ38: 27.65 | BK38: 27.65 | BL38: 27.65 | BM38: 27.65 | BN38: 27.65 | BO38: 27.65 | BP38: 27.65 | BQ38: 27.65 | BR38: 27.65 | BS38: 27.65 | BT38: 27.65 | BU38: 27.65 | BV38: 27.65 | BW38: 27.65 | BX38: 27.65 | BY38: 27.65 | BZ38: 27.65 | CA38: 27.65 | CB38: 27.65 | CC38: 27.65
B40: DOMESTIC: Urban medium
B41: Gas | C41: (p/kWh) | D41: 0.09 | E41: 0.09 | F41: 0.09 | G41: 0.09 | H41: 0.09 | I41: 0.09 | J41: 0.09 | K41: 0.09 | L41: 0.09 | M41: 0.09 | N41: 0.09 | O41: 0.09 | P41: 0.09 | Q41: 0.09 | R41: 0.09 | S41: 0.09 | T41: 0.09 | U41: 0.09 | V41: 0.09 | W41: 0.09 | X41: 0.09 | Y41: 0.09 | Z41: 0.09 | AA41: 0.09 | AB41: 0.09 | AC41: 0.09 | AD41: 0.09 | AE41: 0.09 | AF41: 0.09 | AG41: 0.09 | AH41: 0.09 | AI41: 0.09 | AJ41: 0.09 | AK41: 0.09 | AL41: 0.09 | AM41: 0.09 | AN41: 0.09 | AO41: 0.09 | AP41: 0.09 | AQ41: 0.09 | AR41: 0.09 | AS41: 0.09 | AT41: 0.09 | AU41: 0.09 | AV41: 0.09 | AW41: 0.09 | AX41: 0.09 | AY41: 0.09 | AZ41: 0.09 | BA41: 0.09 | BB41: 0.09 | BC41: 0.09 | BD41: 0.09 | BE41: 0.09 | BF41: 0.09 | BG41: 0.09 | BH41: 0.09 | BI41: 0.09 | BJ41: 0.09 | BK41: 0.09 | BL41: 0.09 | BM41: 0.09 | BN41: 0.09 | BO41: 0.09 | BP41: 0.09 | BQ41: 0.09 | BR41: 0.09 | BS41: 0.09 | BT41: 0.09 | BU41: 0.09 | BV41: 0.09 | BW41: 0.09 | BX41: 0.09 | BY41: 0.09 | BZ41: 0.09 | CA41: 0.09 | CB41: 0.09 | CC41: 0.09
B42: Coal | C42: (p/kWh) | D42: 7.54 | E42: 7.54 | F42: 7.54 | G42: 7.54 | H42: 7.54 | I42: 7.54 | J42: 7.54 | K42: 7.54 | L42: 7.54 | M42: 7.54 | N42: 7.54 | O42: 7.54 | P42: 7.54 | Q42: 7.54 | R42: 7.54 | S42: 7.54 | T42: 7.54 | U42: 7.54 | V42: 7.54 | W42: 7.54 | X42: 7.54 | Y42: 7.54 | Z42: 7.54 | AA42: 7.54 | AB42: 7.54 | AC42: 7.54 | AD42: 7.54 | AE42: 7.54 | AF42: 7.54 | AG42: 7.54 | AH42: 7.54 | AI42: 7.54 | AJ42: 7.54 | AK42: 7.54 | AL42: 7.54 | AM42: 7.54 | AN42: 7.54 | AO42: 7.54 | AP42: 7.54 | AQ42: 7.54 | AR42: 7.54 | AS42: 7.54 | AT42: 7.54 | AU42: 7.54 | AV42: 7.54 | AW42: 7.54 | AX42: 7.54 | AY42: 7.54 | AZ42: 7.54 | BA42: 7.54 | BB42: 7.54 | BC42: 7.54 | BD42: 7.54 | BE42: 7.54 | BF42: 7.54 | BG42: 7.54 | BH42: 7.54 | BI42: 7.54 | BJ42: 7.54 | BK42: 7.54 | BL42: 7.54 | BM42: 7.54 | BN42: 7.54 | BO42: 7.54 | BP42: 7.54 | BQ42: 7.54 | BR42: 7.54 | BS42: 7.54 | BT42: 7.54 | BU42: 7.54 | BV42: 7.54 | BW42: 7.54 | BX42: 7.54 | BY42: 7.54 | BZ42: 7.54 | CA42: 7.54 | CB42: 7.54 | CC42: 7.54
B43: Burning oil | C43: (p/kWh) | D43: 0.21 | E43: 0.21 | F43: 0.21 | G43: 0.21 | H43: 0.21 | I43: 0.21 | J43: 0.21 | K43: 0.21 | L43: 0.21 | M43: 0.21 | N43: 0.21 | O43: 0.21 | P43: 0.21 | Q43: 0.21 | R43: 0.21 | S43: 0.21 | T43: 0.21 | U43: 0.21 | V43: 0.21 | W43: 0.21 | X43: 0.21 | Y43: 0.21 | Z43: 0.21 | AA43: 0.21 | AB43: 0.21 | AC43: 0.21 | AD43: 0.21 | AE43: 0.21 | AF43: 0.21 | AG43: 0.21 | AH43: 0.21 | AI43: 0.21 | AJ43: 0.21 | AK43: 0.21 | AL43: 0.21 | AM43: 0.21 | AN43: 0.21 | AO43: 0.21 | AP43: 0.21 | AQ43: 0.21 | AR43: 0.21 | AS43: 0.21 | AT43: 0.21 | AU43: 0.21 | AV43: 0.21 | AW43: 0.21 | AX43: 0.21 | AY43: 0.21 | AZ43: 0.21 | BA43: 0.21 | BB43: 0.21 | BC43: 0.21 | BD43: 0.21 | BE43: 0.21 | BF43: 0.21 | BG43: 0.21 | BH43: 0.21 | BI43: 0.21 | BJ43: 0.21 | BK43: 0.21 | BL43: 0.21 | BM43: 0.21 | BN43: 0.21 | BO43: 0.21 | BP43: 0.21 | BQ43: 0.21 | BR43: 0.21 | BS43: 0.21 | BT43: 0.21 | BU43: 0.21 | BV43: 0.21 | BW43: 0.21 | BX43: 0.21 | BY43: 0.21 | BZ43: 0.21 | CA43: 0.21 | CB43: 0.21 | CC43: 0.21
B44: Biomass | C44: (p/kWh) | D44: 11.06 | E44: 11.06 | F44: 11.06 | G44: 11.06 | H44: 11.06 | I44: 11.06 | J44: 11.06 | K44: 11.06 | L44: 11.06 | M44: 11.06 | N44: 11.06 | O44: 11.06 | P44: 11.06 | Q44: 11.06 | R44: 11.06 | S44: 11.06 | T44: 11.06 | U44: 11.06 | V44: 11.06 | W44: 11.06 | X44: 11.06 | Y44: 11.06 | Z44: 11.06 | AA44: 11.06 | AB44: 11.06 | AC44: 11.06 | AD44: 11.06 | AE44: 11.06 | AF44: 11.06 | AG44: 11.06 | AH44: 11.06 | AI44: 11.06 | AJ44: 11.06 | AK44: 11.06 | AL44: 11.06 | AM44: 11.06 | AN44: 11.06 | AO44: 11.06 | AP44: 11.06 | AQ44: 11.06 | AR44: 11.06 | AS44: 11.06 | AT44: 11.06 | AU44: 11.06 | AV44: 11.06 | AW44: 11.06 | AX44: 11.06 | AY44: 11.06 | AZ44: 11.06 | BA44: 11.06 | BB44: 11.06 | BC44: 11.06 | BD44: 11.06 | BE44: 11.06 | BF44: 11.06 | BG44: 11.06 | BH44: 11.06 | BI44: 11.06 | BJ44: 11.06 | BK44: 11.06 | BL44: 11.06 | BM44: 11.06 | BN44: 11.06 | BO44: 11.06 | BP44: 11.06 | BQ44: 11.06 | BR44: 11.06 | BS44: 11.06 | BT44: 11.06 | BU44: 11.06 | BV44: 11.06 | BW44: 11.06 | BX44: 11.06 | BY44: 11.06 | BZ44: 11.06 | CA44: 11.06 | CB44: 11.06 | CC44: 11.06
B45: LPG | C45: (p/kWh) | D45: N/A | E45: N/A | F45: N/A | G45: N/A | H45: N/A | I45: N/A | J45: N/A | K45: N/A | L45: N/A | M45: N/A | N45: N/A | O45: N/A | P45: N/A | Q45: N/A | R45: N/A | S45: N/A | T45: N/A | U45: N/A | V45: N/A | W45: N/A | X45: N/A | Y45: N/A | Z45: N/A | AA45: N/A | AB45: N/A | AC45: N/A | AD45: N/A | AE45: N/A | AF45: N/A | AG45: N/A | AH45: N/A | AI45: N/A | AJ45: N/A | AK45: N/A | AL45: N/A | AM45: N/A | AN45: N/A | AO45: N/A | AP45: N/A | AQ45: N/A | AR45: N/A | AS45: N/A | AT45: N/A | AU45: N/A | AV45: N/A | AW45: N/A | AX45: N/A | AY45: N/A | AZ45: N/A | BA45: N/A | BB45: N/A | BC45: N/A | BD45: N/A | BE45: N/A | BF45: N/A | BG45: N/A | BH45: N/A | BI45: N/A | BJ45: N/A | BK45: N/A | BL45: N/A | BM45: N/A | BN45: N/A | BO45: N/A | BP45: N/A | BQ45: N/A | BR45: N/A | BS45: N/A | BT45: N/A | BU45: N/A | BV45: N/A | BW45: N/A | BX45: N/A | BY45: N/A | BZ45: N/A | CA45: N/A | CB45: N/A | CC45: N/A
B46: Peat | C46: (p/kWh) | D46: N/A | E46: N/A | F46: N/A | G46: N/A | H46: N/A | I46: N/A | J46: N/A | K46: N/A | L46: N/A | M46: N/A | N46: N/A | O46: N/A | P46: N/A | Q46: N/A | R46: N/A | S46: N/A | T46: N/A | U46: N/A | V46: N/A | W46: N/A | X46: N/A | Y46: N/A | Z46: N/A | AA46: N/A | AB46: N/A | AC46: N/A | AD46: N/A | AE46: N/A | AF46: N/A | AG46: N/A | AH46: N/A | AI46: N/A | AJ46: N/A | AK46: N/A | AL46: N/A | AM46: N/A | AN46: N/A | AO46: N/A | AP46: N/A | AQ46: N/A | AR46: N/A | AS46: N/A | AT46: N/A | AU46: N/A | AV46: N/A | AW46: N/A | AX46: N/A | AY46: N/A | AZ46: N/A | BA46: N/A | BB46: N/A | BC46: N/A | BD46: N/A | BE46: N/A | BF46: N/A | BG46: N/A | BH46: N/A | BI46: N/A | BJ46: N/A | BK46: N/A | BL46: N/A | BM46: N/A | BN46: N/A | BO46: N/A | BP46: N/A | BQ46: N/A | BR46: N/A | BS46: N/A | BT46: N/A | BU46: N/A | BV46: N/A | BW46: N/A | BX46: N/A | BY46: N/A | BZ46: N/A | CA46: N/A | CB46: N/A | CC46: N/A
B47: Petroleum coke | C47: (p/kWh) | D47: 26.76 | E47: 26.76 | F47: 26.76 | G47: 26.76 | H47: 26.76 | I47: 26.76 | J47: 26.76 | K47: 26.76 | L47: 26.76 | M47: 26.76 | N47: 26.76 | O47: 26.76 | P47: 26.76 | Q47: 26.76 | R47: 26.76 | S47: 26.76 | T47: 26.76 | U47: 26.76 | V47: 26.76 | W47: 26.76 | X47: 26.76 | Y47: 26.76 | Z47: 26.76 | AA47: 26.76 | AB47: 26.76 | AC47: 26.76 | AD47: 26.76 | AE47: 26.76 | AF47: 26.76 | AG47: 26.76 | AH47: 26.76 | AI47: 26.76 | AJ47: 26.76 | AK47: 26.76 | AL47: 26.76 | AM47: 26.76 | AN47: 26.76 | AO47: 26.76 | AP47: 26.76 | AQ47: 26.76 | AR47: 26.76 | AS47: 26.76 | AT47: 26.76 | AU47: 26.76 | AV47: 26.76 | AW47: 26.76 | AX47: 26.76 | AY47: 26.76 | AZ47: 26.76 | BA47: 26.76 | BB47: 26.76 | BC47: 26.76 | BD47: 26.76 | BE47: 26.76 | BF47: 26.76 | BG47: 26.76 | BH47: 26.76 | BI47: 26.76 | BJ47: 26.76 | BK47: 26.76 | BL47: 26.76 | BM47: 26.76 | BN47: 26.76 | BO47: 26.76 | BP47: 26.76 | BQ47: 26.76 | BR47: 26.76 | BS47: 26.76 | BT47: 26.76 | BU47: 26.76 | BV47: 26.76 | BW47: 26.76 | BX47: 26.76 | BY47: 26.76 | BZ47: 26.76 | CA47: 26.76 | CB47: 26.76 | CC47: 26.76
B49: DOMESTIC: Urban small
B50: Gas | C50: (p/kWh) | D50: 0.08 | E50: 0.08 | F50: 0.08 | G50: 0.08 | H50: 0.08 | I50: 0.08 | J50: 0.08 | K50: 0.08 | L50: 0.08 | M50: 0.08 | N50: 0.08 | O50: 0.08 | P50: 0.08 | Q50: 0.08 | R50: 0.08 | S50: 0.08 | T50: 0.08 | U50: 0.08 | V50: 0.08 | W50: 0.08 | X50: 0.08 | Y50: 0.08 | Z50: 0.08 | AA50: 0.08 | AB50: 0.08 | AC50: 0.08 | AD50: 0.08 | AE50: 0.08 | AF50: 0.08 | AG50: 0.08 | AH50: 0.08 | AI50: 0.08 | AJ50: 0.08 | AK50: 0.08 | AL50: 0.08 | AM50: 0.08 | AN50: 0.08 | AO50: 0.08 | AP50: 0.08 | AQ50: 0.08 | AR50: 0.08 | AS50: 0.08 | AT50: 0.08 | AU50: 0.08 | AV50: 0.08 | AW50: 0.08 | AX50: 0.08 | AY50: 0.08 | AZ50: 0.08 | BA50: 0.08 | BB50: 0.08 | BC50: 0.08 | BD50: 0.08 | BE50: 0.08 | BF50: 0.08 | BG50: 0.08 | BH50: 0.08 | BI50: 0.08 | BJ50: 0.08 | BK50: 0.08 | BL50: 0.08 | BM50: 0.08 | BN50: 0.08 | BO50: 0.08 | BP50: 0.08 | BQ50: 0.08 | BR50: 0.08 | BS50: 0.08 | BT50: 0.08 | BU50: 0.08 | BV50: 0.08 | BW50: 0.08 | BX50: 0.08 | BY50: 0.08 | BZ50: 0.08 | CA50: 0.08 | CB50: 0.08 | CC50: 0.08
B51: Coal | C51: (p/kWh) | D51: 6.67 | E51: 6.67 | F51: 6.67 | G51: 6.67 | H51: 6.67 | I51: 6.67 | J51: 6.67 | K51: 6.67 | L51: 6.67 | M51: 6.67 | N51: 6.67 | O51: 6.67 | P51: 6.67 | Q51: 6.67 | R51: 6.67 | S51: 6.67 | T51: 6.67 | U51: 6.67 | V51: 6.67 | W51: 6.67 | X51: 6.67 | Y51: 6.67 | Z51: 6.67 | AA51: 6.67 | AB51: 6.67 | AC51: 6.67 | AD51: 6.67 | AE51: 6.67 | AF51: 6.67 | AG51: 6.67 | AH51: 6.67 | AI51: 6.67 | AJ51: 6.67 | AK51: 6.67 | AL51: 6.67 | AM51: 6.67 | AN51: 6.67 | AO51: 6.67 | AP51: 6.67 | AQ51: 6.67 | AR51: 6.67 | AS51: 6.67 | AT51: 6.67 | AU51: 6.67 | AV51: 6.67 | AW51: 6.67 | AX51: 6.67 | AY51: 6.67 | AZ51: 6.67 | BA51: 6.67 | BB51: 6.67 | BC51: 6.67 | BD51: 6.67 | BE51: 6.67 | BF51: 6.67 | BG51: 6.67 | BH51: 6.67 | BI51: 6.67 | BJ51: 6.67 | BK51: 6.67 | BL51: 6.67 | BM51: 6.67 | BN51: 6.67 | BO51: 6.67 | BP51: 6.67 | BQ51: 6.67 | BR51: 6.67 | BS51: 6.67 | BT51: 6.67 | BU51: 6.67 | BV51: 6.67 | BW51: 6.67 | BX51: 6.67 | BY51: 6.67 | BZ51: 6.67 | CA51: 6.67 | CB51: 6.67 | CC51: 6.67
B52: Burning oil | C52: (p/kWh) | D52: 0.17 | E52: 0.17 | F52: 0.17 | G52: 0.17 | H52: 0.17 | I52: 0.17 | J52: 0.17 | K52: 0.17 | L52: 0.17 | M52: 0.17 | N52: 0.17 | O52: 0.17 | P52: 0.17 | Q52: 0.17 | R52: 0.17 | S52: 0.17 | T52: 0.17 | U52: 0.17 | V52: 0.17 | W52: 0.17 | X52: 0.17 | Y52: 0.17 | Z52: 0.17 | AA52: 0.17 | AB52: 0.17 | AC52: 0.17 | AD52: 0.17 | AE52: 0.17 | AF52: 0.17 | AG52: 0.17 | AH52: 0.17 | AI52: 0.17 | AJ52: 0.17 | AK52: 0.17 | AL52: 0.17 | AM52: 0.17 | AN52: 0.17 | AO52: 0.17 | AP52: 0.17 | AQ52: 0.17 | AR52: 0.17 | AS52: 0.17 | AT52: 0.17 | AU52: 0.17 | AV52: 0.17 | AW52: 0.17 | AX52: 0.17 | AY52: 0.17 | AZ52: 0.17 | BA52: 0.17 | BB52: 0.17 | BC52: 0.17 | BD52: 0.17 | BE52: 0.17 | BF52: 0.17 | BG52: 0.17 | BH52: 0.17 | BI52: 0.17 | BJ52: 0.17 | BK52: 0.17 | BL52: 0.17 | BM52: 0.17 | BN52: 0.17 | BO52: 0.17 | BP52: 0.17 | BQ52: 0.17 | BR52: 0.17 | BS52: 0.17 | BT52: 0.17 | BU52: 0.17 | BV52: 0.17 | BW52: 0.17 | BX52: 0.17 | BY52: 0.17 | BZ52: 0.17 | CA52: 0.17 | CB52: 0.17 | CC52: 0.17
B53: Biomass | C53: (p/kWh) | D53: 8.74 | E53: 8.74 | F53: 8.74 | G53: 8.74 | H53: 8.74 | I53: 8.74 | J53: 8.74 | K53: 8.74 | L53: 8.74 | M53: 8.74 | N53: 8.74 | O53: 8.74 | P53: 8.74 | Q53: 8.74 | R53: 8.74 | S53: 8.74 | T53: 8.74 | U53: 8.74 | V53: 8.74 | W53: 8.74 | X53: 8.74 | Y53: 8.74 | Z53: 8.74 | AA53: 8.74 | AB53: 8.74 | AC53: 8.74 | AD53: 8.74 | AE53: 8.74 | AF53: 8.74 | AG53: 8.74 | AH53: 8.74 | AI53: 8.74 | AJ53: 8.74 | AK53: 8.74 | AL53: 8.74 | AM53: 8.74 | AN53: 8.74 | AO53: 8.74 | AP53: 8.74 | AQ53: 8.74 | AR53: 8.74 | AS53: 8.74 | AT53: 8.74 | AU53: 8.74 | AV53: 8.74 | AW53: 8.74 | AX53: 8.74 | AY53: 8.74 | AZ53: 8.74 | BA53: 8.74 | BB53: 8.74 | BC53: 8.74 | BD53: 8.74 | BE53: 8.74 | BF53: 8.74 | BG53: 8.74 | BH53: 8.74 | BI53: 8.74 | BJ53: 8.74 | BK53: 8.74 | BL53: 8.74 | BM53: 8.74 | BN53: 8.74 | BO53: 8.74 | BP53: 8.74 | BQ53: 8.74 | BR53: 8.74 | BS53: 8.74 | BT53: 8.74 | BU53: 8.74 | BV53: 8.74 | BW53: 8.74 | BX53: 8.74 | BY53: 8.74 | BZ53: 8.74 | CA53: 8.74 | CB53: 8.74 | CC53: 8.74
B54: LPG | C54: (p/kWh) | D54: N/A | E54: N/A | F54: N/A | G54: N/A | H54: N/A | I54: N/A | J54: N/A | K54: N/A | L54: N/A | M54: N/A | N54: N/A | O54: N/A | P54: N/A | Q54: N/A | R54: N/A | S54: N/A | T54: N/A | U54: N/A | V54: N/A | W54: N/A | X54: N/A | Y54: N/A | Z54: N/A | AA54: N/A | AB54: N/A | AC54: N/A | AD54: N/A | AE54: N/A | AF54: N/A | AG54: N/A | AH54: N/A | AI54: N/A | AJ54: N/A | AK54: N/A | AL54: N/A | AM54: N/A | AN54: N/A | AO54: N/A | AP54: N/A | AQ54: N/A | AR54: N/A | AS54: N/A | AT54: N/A | AU54: N/A | AV54: N/A | AW54: N/A | AX54: N/A | AY54: N/A | AZ54: N/A | BA54: N/A | BB54: N/A | BC54: N/A | BD54: N/A | BE54: N/A | BF54: N/A | BG54: N/A | BH54: N/A | BI54: N/A | BJ54: N/A | BK54: N/A | BL54: N/A | BM54: N/A | BN54: N/A | BO54: N/A | BP54: N/A | BQ54: N/A | BR54: N/A | BS54: N/A | BT54: N/A | BU54: N/A | BV54: N/A | BW54: N/A | BX54: N/A | BY54: N/A | BZ54: N/A | CA54: N/A | CB54: N/A | CC54: N/A
B55: Peat | C55: (p/kWh) | D55: N/A | E55: N/A | F55: N/A | G55: N/A | H55: N/A | I55: N/A | J55: N/A | K55: N/A | L55: N/A | M55: N/A | N55: N/A | O55: N/A | P55: N/A | Q55: N/A | R55: N/A | S55: N/A | T55: N/A | U55: N/A | V55: N/A | W55: N/A | X55: N/A | Y55: N/A | Z55: N/A | AA55: N/A | AB55: N/A | AC55: N/A | AD55: N/A | AE55: N/A | AF55: N/A | AG55: N/A | AH55: N/A | AI55: N/A | AJ55: N/A | AK55: N/A | AL55: N/A | AM55: N/A | AN55: N/A | AO55: N/A | AP55: N/A | AQ55: N/A | AR55: N/A | AS55: N/A | AT55: N/A | AU55: N/A | AV55: N/A | AW55: N/A | AX55: N/A | AY55: N/A | AZ55: N/A | BA55: N/A | BB55: N/A | BC55: N/A | BD55: N/A | BE55: N/A | BF55: N/A | BG55: N/A | BH55: N/A | BI55: N/A | BJ55: N/A | BK55: N/A | BL55: N/A | BM55: N/A | BN55: N/A | BO55: N/A | BP55: N/A | BQ55: N/A | BR55: N/A | BS55: N/A | BT55: N/A | BU55: N/A | BV55: N/A | BW55: N/A | BX55: N/A | BY55: N/A | BZ55: N/A | CA55: N/A | CB55: N/A | CC55: N/A
B56: Petroleum coke | C56: (p/kWh) | D56: 26.41 | E56: 26.41 | F56: 26.41 | G56: 26.41 | H56: 26.41 | I56: 26.41 | J56: 26.41 | K56: 26.41 | L56: 26.41 | M56: 26.41 | N56: 26.41 | O56: 26.41 | P56: 26.41 | Q56: 26.41 | R56: 26.41 | S56: 26.41 | T56: 26.41 | U56: 26.41 | V56: 26.41 | W56: 26.41 | X56: 26.41 | Y56: 26.41 | Z56: 26.41 | AA56: 26.41 | AB56: 26.41 | AC56: 26.41 | AD56: 26.41 | AE56: 26.41 | AF56: 26.41 | AG56: 26.41 | AH56: 26.41 | AI56: 26.41 | AJ56: 26.41 | AK56: 26.41 | AL56: 26.41 | AM56: 26.41 | AN56: 26.41 | AO56: 26.41 | AP56: 26.41 | AQ56: 26.41 | AR56: 26.41 | AS56: 26.41 | AT56: 26.41 | AU56: 26.41 | AV56: 26.41 | AW56: 26.41 | AX56: 26.41 | AY56: 26.41 | AZ56: 26.41 | BA56: 26.41 | BB56: 26.41 | BC56: 26.41 | BD56: 26.41 | BE56: 26.41 | BF56: 26.41 | BG56: 26.41 | BH56: 26.41 | BI56: 26.41 | BJ56: 26.41 | BK56: 26.41 | BL56: 26.41 | BM56: 26.41 | BN56: 26.41 | BO56: 26.41 | BP56: 26.41 | BQ56: 26.41 | BR56: 26.41 | BS56: 26.41 | BT56: 26.41 | BU56: 26.41 | BV56: 26.41 | BW56: 26.41 | BX56: 26.41 | BY56: 26.41 | BZ56: 26.41 | CA56: 26.41 | CB56: 26.41 | CC56: 26.41
B58: DOMESTIC: Rural
B59: Gas | C59: p/kWh | D59: 0.06 | E59: 0.06 | F59: 0.06 | G59: 0.06 | H59: 0.06 | I59: 0.06 | J59: 0.06 | K59: 0.06 | L59: 0.06 | M59: 0.06 | N59: 0.06 | O59: 0.06 | P59: 0.06 | Q59: 0.06 | R59: 0.06 | S59: 0.06 | T59: 0.06 | U59: 0.06 | V59: 0.06 | W59: 0.06 | X59: 0.06 | Y59: 0.06 | Z59: 0.06 | AA59: 0.06 | AB59: 0.06 | AC59: 0.06 | AD59: 0.06 | AE59: 0.06 | AF59: 0.06 | AG59: 0.06 | AH59: 0.06 | AI59: 0.06 | AJ59: 0.06 | AK59: 0.06 | AL59: 0.06 | AM59: 0.06 | AN59: 0.06 | AO59: 0.06 | AP59: 0.06 | AQ59: 0.06 | AR59: 0.06 | AS59: 0.06 | AT59: 0.06 | AU59: 0.06 | AV59: 0.06 | AW59: 0.06 | AX59: 0.06 | AY59: 0.06 | AZ59: 0.06 | BA59: 0.06 | BB59: 0.06 | BC59: 0.06 | BD59: 0.06 | BE59: 0.06 | BF59: 0.06 | BG59: 0.06 | BH59: 0.06 | BI59: 0.06 | BJ59: 0.06 | BK59: 0.06 | BL59: 0.06 | BM59: 0.06 | BN59: 0.06 | BO59: 0.06 | BP59: 0.06 | BQ59: 0.06 | BR59: 0.06 | BS59: 0.06 | BT59: 0.06 | BU59: 0.06 | BV59: 0.06 | BW59: 0.06 | BX59: 0.06 | BY59: 0.06 | BZ59: 0.06 | CA59: 0.06 | CB59: 0.06 | CC59: 0.06
B60: Coal | C60: p/kWh | D60: 5.33 | E60: 5.33 | F60: 5.33 | G60: 5.33 | H60: 5.33 | I60: 5.33 | J60: 5.33 | K60: 5.33 | L60: 5.33 | M60: 5.33 | N60: 5.33 | O60: 5.33 | P60: 5.33 | Q60: 5.33 | R60: 5.33 | S60: 5.33 | T60: 5.33 | U60: 5.33 | V60: 5.33 | W60: 5.33 | X60: 5.33 | Y60: 5.33 | Z60: 5.33 | AA60: 5.33 | AB60: 5.33 | AC60: 5.33 | AD60: 5.33 | AE60: 5.33 | AF60: 5.33 | AG60: 5.33 | AH60: 5.33 | AI60: 5.33 | AJ60: 5.33 | AK60: 5.33 | AL60: 5.33 | AM60: 5.33 | AN60: 5.33 | AO60: 5.33 | AP60: 5.33 | AQ60: 5.33 | AR60: 5.33 | AS60: 5.33 | AT60: 5.33 | AU60: 5.33 | AV60: 5.33 | AW60: 5.33 | AX60: 5.33 | AY60: 5.33 | AZ60: 5.33 | BA60: 5.33 | BB60: 5.33 | BC60: 5.33 | BD60: 5.33 | BE60: 5.33 | BF60: 5.33 | BG60: 5.33 | BH60: 5.33 | BI60: 5.33 | BJ60: 5.33 | BK60: 5.33 | BL60: 5.33 | BM60: 5.33 | BN60: 5.33 | BO60: 5.33 | BP60: 5.33 | BQ60: 5.33 | BR60: 5.33 | BS60: 5.33 | BT60: 5.33 | BU60: 5.33 | BV60: 5.33 | BW60: 5.33 | BX60: 5.33 | BY60: 5.33 | BZ60: 5.33 | CA60: 5.33 | CB60: 5.33 | CC60: 5.33
B61: Burning oil | C61: p/kWh | D61: 0.13 | E61: 0.13 | F61: 0.13 | G61: 0.13 | H61: 0.13 | I61: 0.13 | J61: 0.13 | K61: 0.13 | L61: 0.13 | M61: 0.13 | N61: 0.13 | O61: 0.13 | P61: 0.13 | Q61: 0.13 | R61: 0.13 | S61: 0.13 | T61: 0.13 | U61: 0.13 | V61: 0.13 | W61: 0.13 | X61: 0.13 | Y61: 0.13 | Z61: 0.13 | AA61: 0.13 | AB61: 0.13 | AC61: 0.13 | AD61: 0.13 | AE61: 0.13 | AF61: 0.13 | AG61: 0.13 | AH61: 0.13 | AI61: 0.13 | AJ61: 0.13 | AK61: 0.13 | AL61: 0.13 | AM61: 0.13 | AN61: 0.13 | AO61: 0.13 | AP61: 0.13 | AQ61: 0.13 | AR61: 0.13 | AS61: 0.13 | AT61: 0.13 | AU61: 0.13 | AV61: 0.13 | AW61: 0.13 | AX61: 0.13 | AY61: 0.13 | AZ61: 0.13 | BA61: 0.13 | BB61: 0.13 | BC61: 0.13 | BD61: 0.13 | BE61: 0.13 | BF61: 0.13 | BG61: 0.13 | BH61: 0.13 | BI61: 0.13 | BJ61: 0.13 | BK61: 0.13 | BL61: 0.13 | BM61: 0.13 | BN61: 0.13 | BO61: 0.13 | BP61: 0.13 | BQ61: 0.13 | BR61: 0.13 | BS61: 0.13 | BT61: 0.13 | BU61: 0.13 | BV61: 0.13 | BW61: 0.13 | BX61: 0.13 | BY61: 0.13 | BZ61: 0.13 | CA61: 0.13 | CB61: 0.13 | CC61: 0.13
B62: Biomass | C62: p/kWh | D62: 5.54 | E62: 5.54 | F62: 5.54 | G62: 5.54 | H62: 5.54 | I62: 5.54 | J62: 5.54 | K62: 5.54 | L62: 5.54 | M62: 5.54 | N62: 5.54 | O62: 5.54 | P62: 5.54 | Q62: 5.54 | R62: 5.54 | S62: 5.54 | T62: 5.54 | U62: 5.54 | V62: 5.54 | W62: 5.54 | X62: 5.54 | Y62: 5.54 | Z62: 5.54 | AA62: 5.54 | AB62: 5.54 | AC62: 5.54 | AD62: 5.54 | AE62: 5.54 | AF62: 5.54 | AG62: 5.54 | AH62: 5.54 | AI62: 5.54 | AJ62: 5.54 | AK62: 5.54 | AL62: 5.54 | AM62: 5.54 | AN62: 5.54 | AO62: 5.54 | AP62: 5.54 | AQ62: 5.54 | AR62: 5.54 | AS62: 5.54 | AT62: 5.54 | AU62: 5.54 | AV62: 5.54 | AW62: 5.54 | AX62: 5.54 | AY62: 5.54 | AZ62: 5.54 | BA62: 5.54 | BB62: 5.54 | BC62: 5.54 | BD62: 5.54 | BE62: 5.54 | BF62: 5.54 | BG62: 5.54 | BH62: 5.54 | BI62: 5.54 | BJ62: 5.54 | BK62: 5.54 | BL62: 5.54 | BM62: 5.54 | BN62: 5.54 | BO62: 5.54 | BP62: 5.54 | BQ62: 5.54 | BR62: 5.54 | BS62: 5.54 | BT62: 5.54 | BU62: 5.54 | BV62: 5.54 | BW62: 5.54 | BX62: 5.54 | BY62: 5.54 | BZ62: 5.54 | CA62: 5.54 | CB62: 5.54 | CC62: 5.54
B63: LPG | C63: p/kWh | D63: 0.08 | E63: 0.08 | F63: 0.08 | G63: 0.08 | H63: 0.08 | I63: 0.08 | J63: 0.08 | K63: 0.08 | L63: 0.08 | M63: 0.08 | N63: 0.08 | O63: 0.08 | P63: 0.08 | Q63: 0.08 | R63: 0.08 | S63: 0.08 | T63: 0.08 | U63: 0.08 | V63: 0.08 | W63: 0.08 | X63: 0.08 | Y63: 0.08 | Z63: 0.08 | AA63: 0.08 | AB63: 0.08 | AC63: 0.08 | AD63: 0.08 | AE63: 0.08 | AF63: 0.08 | AG63: 0.08 | AH63: 0.08 | AI63: 0.08 | AJ63: 0.08 | AK63: 0.08 | AL63: 0.08 | AM63: 0.08 | AN63: 0.08 | AO63: 0.08 | AP63: 0.08 | AQ63: 0.08 | AR63: 0.08 | AS63: 0.08 | AT63: 0.08 | AU63: 0.08 | AV63: 0.08 | AW63: 0.08 | AX63: 0.08 | AY63: 0.08 | AZ63: 0.08 | BA63: 0.08 | BB63: 0.08 | BC63: 0.08 | BD63: 0.08 | BE63: 0.08 | BF63: 0.08 | BG63: 0.08 | BH63: 0.08 | BI63: 0.08 | BJ63: 0.08 | BK63: 0.08 | BL63: 0.08 | BM63: 0.08 | BN63: 0.08 | BO63: 0.08 | BP63: 0.08 | BQ63: 0.08 | BR63: 0.08 | BS63: 0.08 | BT63: 0.08 | BU63: 0.08 | BV63: 0.08 | BW63: 0.08 | BX63: 0.08 | BY63: 0.08 | BZ63: 0.08 | CA63: 0.08 | CB63: 0.08 | CC63: 0.08
B64: Peat | C64: p/kWh | D64: N/A | E64: N/A | F64: N/A | G64: N/A | H64: N/A | I64: N/A | J64: N/A | K64: N/A | L64: N/A | M64: N/A | N64: N/A | O64: N/A | P64: N/A | Q64: N/A | R64: N/A | S64: N/A | T64: N/A | U64: N/A | V64: N/A | W64: N/A | X64: N/A | Y64: N/A | Z64: N/A | AA64: N/A | AB64: N/A | AC64: N/A | AD64: N/A | AE64: N/A | AF64: N/A | AG64: N/A | AH64: N/A | AI64: N/A | AJ64: N/A | AK64: N/A | AL64: N/A | AM64: N/A | AN64: N/A | AO64: N/A | AP64: N/A | AQ64: N/A | AR64: N/A | AS64: N/A | AT64: N/A | AU64: N/A | AV64: N/A | AW64: N/A | AX64: N/A | AY64: N/A | AZ64: N/A | BA64: N/A | BB64: N/A | BC64: N/A | BD64: N/A | BE64: N/A | BF64: N/A | BG64: N/A | BH64: N/A | BI64: N/A | BJ64: N/A | BK64: N/A | BL64: N/A | BM64: N/A | BN64: N/A | BO64: N/A | BP64: N/A | BQ64: N/A | BR64: N/A | BS64: N/A | BT64: N/A | BU64: N/A | BV64: N/A | BW64: N/A | BX64: N/A | BY64: N/A | BZ64: N/A | CA64: N/A | CB64: N/A | CC64: N/A
B65: Petroleum coke | C65: p/kWh | D65: 25.91 | E65: 25.91 | F65: 25.91 | G65: 25.91 | H65: 25.91 | I65: 25.91 | J65: 25.91 | K65: 25.91 | L65: 25.91 | M65: 25.91 | N65: 25.91 | O65: 25.91 | P65: 25.91 | Q65: 25.91 | R65: 25.91 | S65: 25.91 | T65: 25.91 | U65: 25.91 | V65: 25.91 | W65: 25.91 | X65: 25.91 | Y65: 25.91 | Z65: 25.91 | AA65: 25.91 | AB65: 25.91 | AC65: 25.91 | AD65: 25.91 | AE65: 25.91 | AF65: 25.91 | AG65: 25.91 | AH65: 25.91 | AI65: 25.91 | AJ65: 25.91 | AK65: 25.91 | AL65: 25.91 | AM65: 25.91 | AN65: 25.91 | AO65: 25.91 | AP65: 25.91 | AQ65: 25.91 | AR65: 25.91 | AS65: 25.91 | AT65: 25.91 | AU65: 25.91 | AV65: 25.91 | AW65: 25.91 | AX65: 25.91 | AY65: 25.91 | AZ65: 25.91 | BA65: 25.91 | BB65: 25.91 | BC65: 25.91 | BD65: 25.91 | BE65: 25.91 | BF65: 25.91 | BG65: 25.91 | BH65: 25.91 | BI65: 25.91 | BJ65: 25.91 | BK65: 25.91 | BL65: 25.91 | BM65: 25.91 | BN65: 25.91 | BO65: 25.91 | BP65: 25.91 | BQ65: 25.91 | BR65: 25.91 | BS65: 25.91 | BT65: 25.91 | BU65: 25.91 | BV65: 25.91 | BW65: 25.91 | BX65: 25.91 | BY65: 25.91 | BZ65: 25.91 | CA65: 25.91 | CB65: 25.91 | CC65: 25.91
B67: Source: Defra
B69: Definitions of the areas are taken from the DfT National Transport model and can be found in the link below in table A2:
B70: https://www.gov.uk/government/uploads/system/uploads/attachment_data/file/286935/webtag-tag-unit-a5-4-marginal-external-congestion-costs.pdf
B72: Defra's Air Quality Guidance can be found at:
B73: https://www.gov.uk/government/publications/assess-the-impact-of-air-quality
B75: For further information on valuing Air Quality impacts, contact the IGCB:
B76: igcb@defra.gsi.gov.uk

Sheet UK ETS
A1: Source: https://www.gov.uk/government/publications/traded-carbon-values-used-for-modelling-purposes-2023/traded-carbon-values-used-for-modelling-purposes-2023
A4: Table 1: Traded carbon values for modelling purposes, £/tCO2e (real 2023)
A6: Year | B6: Market Carbon Values | C6: Low Sensitivity - High Fossil Fuel Prices and Low Economic Growth | D6: Net Zero Strategy Aligned | E6: High Sensitivity – Low Fossil Fuel Prices and High Economic Growth
B7: (2023 GBP) | C7: (2023 GBP) | D7: (2023 GBP) | E7: (2023 GBP)
A8: 2023 | B8: 70 | C8: 51 | D8: 59 | E8: 64
A9: 2024 | B9: 72 | C9: 63 | D9: 76 | E9: 84
A10: 2025 | B10: 79 | C10: 71 | D10: 88 | E10: 100
A11: 2026 | B11: 91 | C11: 77 | D11: 98 | E11: 114
A12: 2027 | B12: 97 | C12: 73 | D12: 97 | E12: 116
A13: 2028 | B13: 98 | C13: 69 | D13: 98 | E13: 124
A14: 2029 | B14: 89 | C14: 58 | D14: 89 | E14: 118
A15: 2030 | B15: 87 | C15: 56 | D15: 87 | E15: 118
A16: 2031 | B16: 94 | C16: 60 | D16: 94 | E16: 128
A17: 2032 | B17: 101 | C17: 67 | D17: 101 | E17: 131
A18: 2033 | B18: 108 | C18: 70 | D18: 108 | E18: 136
A19: 2034 | B19: 111 | C19: 72 | D19: 111 | E19: 139
... A35: 2050 | B35: 138 | C35: 95 | D35: 138 | E35: 172

Sheet WattTime marginal carbon intens
A1: Data in https://docs.google.com/spreadsheets/d/1xjG6cSkeIY839OLXHg10fQ-mqQQ66oiDxlozq-F0rL4/edit?gid=732718702#gid=732718702
B3: Non-weighted average (gCO2eq/kWh) | D3: 2022 | E3: 2023 | F3: 2024
A4: Peak | B4: 0.66666667 | C4: 0.79166667 | D4: 447.5 | E4: 439.51 | F4: 447.47
A5: Normal rate | B5: OTHER | D5: 424.74 | E5: 418.67 | F5: 419.88
A6: Off-peak nigth | B6: 0.16666667 | C6: 0.29166667 | D6: 417.76 | E6: 407.17 | F6: 405.51
A7: Off-peak afternoon | B7: 0.54166667 | C7: 0.66666667 | D7: 432.85 | E7: 423.8 | F7: 424.02

Sheet System price
A1: Source: LCPEnact
A4: Settlement | B4: 2022 | C4: 2023 | D4: Jan-Jun 15th 2024 | G4: =B4 | H4: =C4 | I4: 2024
A5: 1 | B5: 169.25047 | C5: 82.048301 | D5: 56.540778 | E5: 12 | F5: Overnight cosy 4am to 7am | G5: =average(B13:B18) | H5: =average(C13:C18) | I5: =average(D13:D18)
A6: 2 | B6: 177.99874 | C6: 84.931621 | D6: 58.675723 | E6: 12 | F6: Day cosy 1pm to 4pm | G6: =average(B31:B36) | H6: =average(C31:C36) | I6: =average(D31:D36)
A7: 3 | B7: 174.36434 | C7: 80.798462 | D7: 55.212485 | E7: 1 | F7: Peak | G7: =AVERAGE(B37:B42) | H7: =AVERAGE(C37:C42) | I7: =AVERAGE(D37:D42)
A8: 4 | B8: 166.27887 | C8: 76.956456 | D8: 50.754242 | E8: 1 | F8: Other | G8: =average(B5:B12,B19:B30,B43:B52) | H8: =average(C5:C12,C19:C30,C43:C52) | I8: =average(D5:D12,D19:D30,D43:D52)
A9: 5 | B9: 165.84467 | C9: 76.361236 | D9: 48.452108 | E9: 2
A10: 6 | B10: 156.50242 | C10: 72.234396 | D10: 48.616325 | E10: 2
A11: 7 | B11: 162.79316 | C11: 73.651456 | D11: 50.293855 | E11: 3
A12: 8 | B12: 150.73995 | C12: 69.56467 | D12: 49.358614 | E12: 3
A13: 9 | B13: 162.56555 | C13: 73.390635 | D13: 52.504819 | E13: 4
A14: 10 | B14: 156.85923 | C14: 68.538039 | D14: 47.227108 | E14: 4
A15: 11 | B15: 164.06077 | C15: 77.30876 | D15: 53.449639 | E15: 5
A16: 12 | B16: 168.92937 | C16: 80.839286 | D16: 51.863012 | E16: 5
A17: 13 | B17: 189.70376 | C17: 89.632445 | D17: 57.964036 | E17: 6
A18: 14 | B18: 208.09176 | C18: 100.06868 | D18: 67.272892 | E18: 6
A19: 15 | B19: 202.91047 | C19: 94.9275 | D19: 66.801446 | E19: 7
A20: 16 | B20: 237.26783 | C20: 113.9994 | D20: 75.220301 | E20: 7
... A52: 48 | B52: 180.96789 | C52: 81.752782 | D52: 59.458855 | E52: 23

Sheet MCS cost data
A1: Source: https://datadashboard.mcscertified.com/InstallationInsights
A3: Month | B3: Average installation cost per kW (£) | C3: Average installation cost (£)
A4: 45311 | B4: 1146 | C4: 10661
A5: 45342 | B5: 1130 | C5: 10914
A6: 45371 | B6: 1135 | C6: 11370
A7: 45402 | B7: 1152 | C7: 11636
A8: 45432 | B8: 1111 | C8: 11590
A9: 45463 | B9: 1082 | C9: 11183
A10: 45493 | B10: 1111 | C10: 11279
A11: 45524 | B11: 1156 | C11: 11744
A12: 45555 | B12: 1137 | C12: 11437
A13: 45585 | B13: 1145 | C13: 11171
A14: 45616 | B14: 1172 | C14: 10984
A15: 45646 | B15: 1184 | C15: 11709
... A56: 45436 | B56: 1454 | C56: 12698
A57: 45467 | B57: 1469 | C57: 12667 | F57: =average(C50:C57)
A58: 45497 | B58: 1505 | C58: 12980
